[{"id": "901411773085036544", "text": "RT @NWSFortWorth: Showers/tstorms likely along &amp; S of a Goldthwaite-Hillsboro-Palestine line.Flash Flood Watch in outlined area.\u2026 ", "created_at": {"$date": "2017-08-26T11:51:28Z"}, "favorites_count": 0, "user": {"screen_name": "NavarroOEM", "name": "Navarro County OEM", "id": "821709997", "friends": 1428, "followers": 2524, "verified": false, "account_created_at": {"$date": "2012-09-13T15:32:52Z"}, "location": "Corsicana, TX", "description": "The Navarro County Office of Emergency Management (NCOEM) serves Navarro County in preparing for and responding to emergencies and disasters."}, "original_text": "Showers/tstorms likely along &amp; S of a Goldthwaite-Hillsboro-Palestine line.Flash Flood Watch in outlined area.\u2026 https://t.co/LSOL4n5ELZ", "id2": "901392162797084672", "tweet_types": {"deleted_tweet": 0, "retweet": "901392162797084672", "quote_tweet": 0, "reply": 0, "original_tweet": 0}}, {"id": "901420460956688384", "text": "RT @NWSFortWorth: Showers/tstorms likely along &amp; S of a Goldthwaite-Hillsboro-Palestine line.Flash Flood Watch in outlined area.\u2026 ", "created_at": {"$date": "2017-08-26T12:26:00Z"}, "favorites_count": 0, "user": {"screen_name": "hctxnow", "name": "Henderson County Now", "id": "2656354204", "friends": 113, "followers": 1679, "verified": false, "account_created_at": {"$date": "2014-06-30T12:04:43Z"}, "location": "Athens, Texas", "description": "News and events to facilitate community connections brought to you by Weinstein Law, Uncle Fletch and Weinstein Real Estate. - Instagram @hctxnow"}, "original_text": "Showers/tstorms likely along &amp; S of a Goldthwaite-Hillsboro-Palestine line.Flash Flood Watch in outlined area.\u2026 https://t.co/LSOL4n5ELZ", "id2": "901392162797084672", "tweet_types": {"deleted_tweet": 0, "retweet": "901392162797084672", "quote_tweet": 0, "reply": 0, "original_tweet": 0}}, {"id": "901437045612171264", "text": "RT @NWSFortWorth: Showers/tstorms likely along &amp; S of a Goldthwaite-Hillsboro-Palestine line.Flash Flood Watch in outlined area.\u2026 ", "created_at": {"$date": "2017-08-26T13:31:54Z"}, "favorites_count": 0, "user": {"screen_name": "ctgdentoncounty", "name": "CrossTimbersGazette", "id": "14577112", "friends": 357, "followers": 3288, "verified": false, "account_created_at": {"$date": "2008-04-28T23:07:03Z"}, "location": "Flower Mound, TX", "description": "The Cross Timbers Gazette newspaper - Your Link to southern Denton County, TX since 1979."}, "original_text": "Showers/tstorms likely along &amp; S of a Goldthwaite-Hillsboro-Palestine line.Flash Flood Watch in outlined area.\u2026 https://t.co/LSOL4n5ELZ", "id2": "901392162797084672", "tweet_types": {"deleted_tweet": 0, "retweet": "901392162797084672", "quote_tweet": 0, "reply": 0, "original_tweet": 0}}, {"id": "901442288173412353", "text": "RT @NWSFortWorth: Showers/tstorms likely along &amp; S of a Goldthwaite-Hillsboro-Palestine line.Flash Flood Watch in outlined area.\u2026 ", "created_at": {"$date": "2017-08-26T13:52:44Z"}, "favorites_count": 0, "user": {"screen_name": "K5OUN", "name": "K5OUN", "id": "515066914", "friends": 145, "followers": 92, "verified": false, "account_created_at": {"$date": "2012-03-05T03:54:40Z"}, "location": "DFW TX.", "description": null}, "original_text": "Showers/tstorms likely along &amp; S of a Goldthwaite-Hillsboro-Palestine line.Flash Flood Watch in outlined area.\u2026 https://t.co/LSOL4n5ELZ", "id2": "901392162797084672", "tweet_types": {"deleted_tweet": 0, "retweet": "901392162797084672", "quote_tweet": 0, "reply": 0, "original_tweet": 0}}, {"id": "901443190489743360", "text": "RT @NWSFortWorth: Showers/tstorms likely along &amp; S of a Goldthwaite-Hillsboro-Palestine line.Flash Flood Watch in outlined area.\u2026 ", "created_at": {"$date": "2017-08-26T13:56:19Z"}, "favorites_count": 0, "user": {"screen_name": "Texas_Badger", "name": "Matthew Knauf, M.S.", "id": "721133778", "friends": 361, "followers": 293, "verified": false, "account_created_at": {"$date": "2012-07-28T00:08:03Z"}, "location": "Texas, USA", "description": "U.-Wisconsin Alum, Badger 4 Life. Teacher/Coach, Apple T/Google Cert. Pug dad. Conservative. Faith, Family, Friends, Freedom, Firearms. My Tweets R My Own."}, "original_text": "Showers/tstorms likely along &amp; S of a Goldthwaite-Hillsboro-Palestine line.Flash Flood Watch in outlined area.\u2026 https://t.co/LSOL4n5ELZ", "id2": "901392162797084672", "tweet_types": {"deleted_tweet": 0, "retweet": "901392162797084672", "quote_tweet": 0, "reply": 0, "original_tweet": 0}}, {"id": "901407357372125185", "text": "RT @NWSFortWorth: Showers/tstorms likely along &amp; S of a Goldthwaite-Hillsboro-Palestine line.Flash Flood Watch in outlined area.\u2026 ", "created_at": {"$date": "2017-08-26T11:33:55Z"}, "favorites_count": 0, "user": {"screen_name": "Wackotreehugger", "name": "Don Alexander", "id": "1546935138", "friends": 605, "followers": 67, "verified": false, "account_created_at": {"$date": "2013-06-26T00:28:18Z"}, "description": null}, "original_text": "Showers/tstorms likely along &amp; S of a Goldthwaite-Hillsboro-Palestine line.Flash Flood Watch in outlined area.\u2026 https://t.co/LSOL4n5ELZ", "id2": "901392162797084672", "tweet_types": {"deleted_tweet": 0, "retweet": "901392162797084672", "quote_tweet": 0, "reply": 0, "original_tweet": 0}}, {"id": "901396982358528000", "text": "RT @NWSFortWorth: Showers/tstorms likely along &amp; S of a Goldthwaite-Hillsboro-Palestine line.Flash Flood Watch in outlined area.\u2026 ", "created_at": {"$date": "2017-08-26T10:52:42Z"}, "favorites_count": 0, "user": {"screen_name": "mccoyshawn144", "name": "ShyGuyFan", "id": "2790763820", "friends": 982, "followers": 274, "verified": false, "account_created_at": {"$date": "2014-09-04T23:02:50Z"}, "location": "Dallas, TX", "description": "I am a huge Nintendo Fan, do YouTube videos and play Wii U, 3DS, and Switch games. Hype for Battlefront 2. Back to school on August 28 for me."}, "original_text": "Showers/tstorms likely along &amp; S of a Goldthwaite-Hillsboro-Palestine line.Flash Flood Watch in outlined area.\u2026 https://t.co/LSOL4n5ELZ", "id2": "901392162797084672", "tweet_types": {"deleted_tweet": 0, "retweet": "901392162797084672", "quote_tweet": 0, "reply": 0, "original_tweet": 0}}, {"id": "901392301632651264", "text": "RT @NWSFortWorth: Showers/tstorms likely along &amp; S of a Goldthwaite-Hillsboro-Palestine line.Flash Flood Watch in outlined area.\u2026 ", "created_at": {"$date": "2017-08-26T10:34:06Z"}, "favorites_count": 0, "user": {"screen_name": "GraysonCounty", "name": "Grayson County OEM", "id": "44794344", "friends": 602, "followers": 3243, "verified": false, "account_created_at": {"$date": "2009-06-05T02:06:26Z"}, "location": "Texas", "description": "Official Twitter account of the Grayson County Office of Emergency Management serving the people of Grayson County and its sixteen cities"}, "original_text": "Showers/tstorms likely along &amp; S of a Goldthwaite-Hillsboro-Palestine line.Flash Flood Watch in outlined area.\u2026 https://t.co/LSOL4n5ELZ", "id2": "901392162797084672", "tweet_types": {"deleted_tweet": 0, "retweet": "901392162797084672", "quote_tweet": 0, "reply": 0, "original_tweet": 0}}, {"id": "901392633901318144", "text": "RT @NWSFortWorth: Showers/tstorms likely along &amp; S of a Goldthwaite-Hillsboro-Palestine line.Flash Flood Watch in outlined area.\u2026 ", "created_at": {"$date": "2017-08-26T10:35:25Z"}, "favorites_count": 0, "user": {"screen_name": "TeckieGirl", "name": "TeckieGirl \ud83d\udc96\ud83d\udd25\u270a\ud83c\udffd", "id": "25661441", "friends": 3129, "followers": 4121, "verified": false, "account_created_at": {"$date": "2009-03-21T10:39:27Z"}, "location": "Dallas TX", "description": "Lover of Jesus, life, cookies and milk, #Ghostbuster fan since 1984, love design,dance and technology. I still have faith in man kind.#petparent #foodie #resist"}, "original_text": "Showers/tstorms likely along &amp; S of a Goldthwaite-Hillsboro-Palestine line.Flash Flood Watch in outlined area.\u2026 https://t.co/LSOL4n5ELZ", "id2": "901392162797084672", "tweet_types": {"deleted_tweet": 0, "retweet": "901392162797084672", "quote_tweet": 0, "reply": 0, "original_tweet": 0}}]