[{"id": "901377322426802177", "text": "RT @NWSHouston: Tornado Warning including Sugar Land TX, Pecan Grove TX, New Territory TX until 2:30 AM CDT https://t.co/nzIqImtIzu", "created_at": {"$date": "2017-08-26T09:34:35Z"}, "favorites_count": 0, "user": {"screen_name": "StevePh49215783", "name": "SP Phillips", "id": "987820603", "friends": 4972, "followers": 2982, "verified": false, "account_created_at": {"$date": "2012-12-04T01:48:46Z"}, "location": "Florida, USA", "description": "Love my family. Love America. America will survive based on its principles. Hate & racism will lose. #TheResistance #Resist #Resistance"}, "original_text": "Tornado Warning including Sugar Land TX, Pecan Grove TX, New Territory TX until 2:30 AM CDT https://t.co/nzIqImtIzu", "id2": "901341244319780864", "tweet_types": {"deleted_tweet": 0, "retweet": "901341244319780864", "quote_tweet": 0, "reply": 0, "original_tweet": 0}}, {"id": "901343708175642625", "text": "RT @NWSHouston: Tornado Warning including Sugar Land TX, Pecan Grove TX, New Territory TX until 2:30 AM CDT https://t.co/nzIqImtIzu", "created_at": {"$date": "2017-08-26T07:21:00Z"}, "favorites_count": 0, "user": {"screen_name": "asmazmohd", "name": "Asma Mohd", "id": "124957629", "friends": 174, "followers": 194, "verified": false, "account_created_at": {"$date": "2010-03-21T05:14:24Z"}, "description": "\ud83e\udd18\ud83c\udffd"}, "original_text": "Tornado Warning including Sugar Land TX, Pecan Grove TX, New Territory TX until 2:30 AM CDT https://t.co/nzIqImtIzu", "id2": "901341244319780864", "tweet_types": {"deleted_tweet": 0, "retweet": "901341244319780864", "quote_tweet": 0, "reply": 0, "original_tweet": 0}}, {"id": "901344515063197696", "text": "RT @NWSHouston: Tornado Warning including Sugar Land TX, Pecan Grove TX, New Territory TX until 2:30 AM CDT https://t.co/nzIqImtIzu", "created_at": {"$date": "2017-08-26T07:24:13Z"}, "favorites_count": 0, "user": {"screen_name": "igetsnolove_", "name": "Erin Nicole \ud83d\udc51", "id": "1485865932", "friends": 1228, "followers": 1368, "verified": false, "account_created_at": {"$date": "2013-06-05T19:59:42Z"}, "location": "HTX", "description": "19."}, "original_text": "Tornado Warning including Sugar Land TX, Pecan Grove TX, New Territory TX until 2:30 AM CDT https://t.co/nzIqImtIzu", "id2": "901341244319780864", "tweet_types": {"deleted_tweet": 0, "retweet": "901341244319780864", "quote_tweet": 0, "reply": 0, "original_tweet": 0}}, {"id": "901344702104055808", "text": "RT @NWSHouston: Tornado Warning including Sugar Land TX, Pecan Grove TX, New Territory TX until 2:30 AM CDT https://t.co/nzIqImtIzu", "created_at": {"$date": "2017-08-26T07:24:57Z"}, "favorites_count": 0, "user": {"screen_name": "MaddiJMays", "name": "Maddi Mays", "id": "1147072682", "friends": 366, "followers": 1596, "verified": false, "account_created_at": {"$date": "2013-02-04T04:57:23Z"}, "location": "Houston, TX", "description": "art | design [black\u2022white\u2022filipino]"}, "original_text": "Tornado Warning including Sugar Land TX, Pecan Grove TX, New Territory TX until 2:30 AM CDT https://t.co/nzIqImtIzu", "id2": "901341244319780864", "tweet_types": {"deleted_tweet": 0, "retweet": "901341244319780864", "quote_tweet": 0, "reply": 0, "original_tweet": 0}}, {"id": "901344784333373441", "text": "RT @NWSHouston: Tornado Warning including Sugar Land TX, Pecan Grove TX, New Territory TX until 2:30 AM CDT https://t.co/nzIqImtIzu", "created_at": {"$date": "2017-08-26T07:25:17Z"}, "favorites_count": 0, "user": {"screen_name": "Misbaah_", "name": "Misbaah Mak", "id": "2292279460", "friends": 341, "followers": 438, "verified": false, "account_created_at": {"$date": "2014-01-19T20:07:05Z"}, "description": "United States Of Houston."}, "original_text": "Tornado Warning including Sugar Land TX, Pecan Grove TX, New Territory TX until 2:30 AM CDT https://t.co/nzIqImtIzu", "id2": "901341244319780864", "tweet_types": {"deleted_tweet": 0, "retweet": "901341244319780864", "quote_tweet": 0, "reply": 0, "original_tweet": 0}}, {"id": "901345183643684865", "text": "RT @NWSHouston: Tornado Warning including Sugar Land TX, Pecan Grove TX, New Territory TX until 2:30 AM CDT https://t.co/nzIqImtIzu", "created_at": {"$date": "2017-08-26T07:26:52Z"}, "favorites_count": 0, "user": {"screen_name": "alishaan_m", "name": "Alishaan Momin", "id": "4445552894", "friends": 114, "followers": 131, "verified": false, "account_created_at": {"$date": "2015-12-03T20:40:46Z"}, "description": "CHS '19"}, "original_text": "Tornado Warning including Sugar Land TX, Pecan Grove TX, New Territory TX until 2:30 AM CDT https://t.co/nzIqImtIzu", "id2": "901341244319780864", "tweet_types": {"deleted_tweet": 0, "retweet": "901341244319780864", "quote_tweet": 0, "reply": 0, "original_tweet": 0}}, {"id": "901345169307557888", "text": "RT @NWSHouston: Tornado Warning including Sugar Land TX, Pecan Grove TX, New Territory TX until 2:30 AM CDT https://t.co/nzIqImtIzu", "created_at": {"$date": "2017-08-26T07:26:49Z"}, "favorites_count": 0, "user": {"screen_name": "tx_pierce", "name": "matt pierce", "id": "23633215", "friends": 2717, "followers": 4780, "verified": false, "account_created_at": {"$date": "2009-03-10T18:56:45Z"}, "location": "\u00dcT: 29.704023,-95.815787 ", "description": "Head Baseball Hou Christian/South Texas Sliders Recruiting Coordinator/SW Reg Director of https://t.co/39OX9nSqfh \n@elite_baseball/sequentialbaseballtraining.com"}, "original_text": "Tornado Warning including Sugar Land TX, Pecan Grove TX, New Territory TX until 2:30 AM CDT https://t.co/nzIqImtIzu", "id2": "901341244319780864", "tweet_types": {"deleted_tweet": 0, "retweet": "901341244319780864", "quote_tweet": 0, "reply": 0, "original_tweet": 0}}, {"id": "901341312175177728", "text": "RT @NWSHouston: Tornado Warning including Sugar Land TX, Pecan Grove TX, New Territory TX until 2:30 AM CDT https://t.co/nzIqImtIzu", "created_at": {"$date": "2017-08-26T07:11:29Z"}, "favorites_count": 0, "user": {"screen_name": "UHMarisa", "name": "UHMarisa", "id": "17212123", "friends": 858, "followers": 690, "verified": false, "account_created_at": {"$date": "2008-11-06T14:52:59Z"}, "location": "Houston, Texas", "description": "Executive Director of Communications UH Sugar Land. Need an expert? Let me know here or mrcannon@uh.edu. GO COOGS!"}, "original_text": "Tornado Warning including Sugar Land TX, Pecan Grove TX, New Territory TX until 2:30 AM CDT https://t.co/nzIqImtIzu", "id2": "901341244319780864", "tweet_types": {"deleted_tweet": 0, "retweet": "901341244319780864", "quote_tweet": 0, "reply": 0, "original_tweet": 0}}, {"id": "901341377283448833", "text": "RT @NWSHouston: Tornado Warning including Sugar Land TX, Pecan Grove TX, New Territory TX until 2:30 AM CDT https://t.co/nzIqImtIzu", "created_at": {"$date": "2017-08-26T07:11:45Z"}, "favorites_count": 0, "user": {"screen_name": "TRASHANDBASHH", "name": "PNG./JPEG./PDF.", "id": "2849030433", "friends": 831, "followers": 1786, "verified": false, "account_created_at": {"$date": "2014-10-29T00:02:20Z"}, "location": "NFR.", "description": null}, "original_text": "Tornado Warning including Sugar Land TX, Pecan Grove TX, New Territory TX until 2:30 AM CDT https://t.co/nzIqImtIzu", "id2": "901341244319780864", "tweet_types": {"deleted_tweet": 0, "retweet": "901341244319780864", "quote_tweet": 0, "reply": 0, "original_tweet": 0}}, {"id": "901341285033938944", "text": "RT @NWSHouston: Tornado Warning including Sugar Land TX, Pecan Grove TX, New Territory TX until 2:30 AM CDT https://t.co/nzIqImtIzu", "created_at": {"$date": "2017-08-26T07:11:23Z"}, "favorites_count": 0, "user": {"screen_name": "TxStormChasers", "name": "Texas Storm Chasers", "id": "27557391", "friends": 101275, "followers": 213807, "verified": true, "account_created_at": {"$date": "2009-03-30T01:49:47Z"}, "location": "Cedar Hill, TX", "description": "Source of Texas Weather Information \u2022  Always hunting for the next storm to document \u2022 Doesn't read DMs! \u2022 Tweets usually from David Reimer"}, "original_text": "Tornado Warning including Sugar Land TX, Pecan Grove TX, New Territory TX until 2:30 AM CDT https://t.co/nzIqImtIzu", "id2": "901341244319780864", "tweet_types": {"deleted_tweet": 0, "retweet": "901341244319780864", "quote_tweet": 0, "reply": 0, "original_tweet": 0}}, {"id": "901341595500457984", "text": "RT @NWSHouston: Tornado Warning including Sugar Land TX, Pecan Grove TX, New Territory TX until 2:30 AM CDT https://t.co/nzIqImtIzu", "created_at": {"$date": "2017-08-26T07:12:37Z"}, "favorites_count": 0, "user": {"screen_name": "mshell86", "name": "Michele Cooper", "id": "285793483", "friends": 117, "followers": 82, "verified": false, "account_created_at": {"$date": "2011-04-21T20:03:01Z"}, "location": "Texas", "description": "I am the single mom of 2 great kids Brice and Emily. I took early retirement from ATT after 20 years and now I just enjoy my life!!"}, "original_text": "Tornado Warning including Sugar Land TX, Pecan Grove TX, New Territory TX until 2:30 AM CDT https://t.co/nzIqImtIzu", "id2": "901341244319780864", "tweet_types": {"deleted_tweet": 0, "retweet": "901341244319780864", "quote_tweet": 0, "reply": 0, "original_tweet": 0}}, {"id": "901341597941600256", "text": "RT @NWSHouston: Tornado Warning including Sugar Land TX, Pecan Grove TX, New Territory TX until 2:30 AM CDT https://t.co/nzIqImtIzu", "created_at": {"$date": "2017-08-26T07:12:37Z"}, "favorites_count": 0, "user": {"screen_name": "twright55", "name": "Tatiana Wright", "id": "93288759", "friends": 808, "followers": 9620, "verified": false, "account_created_at": {"$date": "2009-11-29T00:17:35Z"}, "location": "Tysons Corner, VA", "description": "I am just #Tatiana, #Republican. The Politician. Proud American. #MAGA #AmericaFirst"}, "original_text": "Tornado Warning including Sugar Land TX, Pecan Grove TX, New Territory TX until 2:30 AM CDT https://t.co/nzIqImtIzu", "id2": "901341244319780864", "tweet_types": {"deleted_tweet": 0, "retweet": "901341244319780864", "quote_tweet": 0, "reply": 0, "original_tweet": 0}}, {"id": "901341603641643008", "text": "RT @NWSHouston: Tornado Warning including Sugar Land TX, Pecan Grove TX, New Territory TX until 2:30 AM CDT https://t.co/nzIqImtIzu", "created_at": {"$date": "2017-08-26T07:12:39Z"}, "favorites_count": 0, "user": {"screen_name": "joshuatcarley", "name": "Joshua T Carley", "id": "888323991504551936", "friends": 5001, "followers": 301, "verified": false, "account_created_at": {"$date": "2017-07-21T09:05:18Z"}, "location": "Houston, TX", "description": null}, "original_text": "Tornado Warning including Sugar Land TX, Pecan Grove TX, New Territory TX until 2:30 AM CDT https://t.co/nzIqImtIzu", "id2": "901341244319780864", "tweet_types": {"deleted_tweet": 0, "retweet": "901341244319780864", "quote_tweet": 0, "reply": 0, "original_tweet": 0}}, {"id": "901341735539945472", "text": "RT @NWSHouston: Tornado Warning including Sugar Land TX, Pecan Grove TX, New Territory TX until 2:30 AM CDT https://t.co/nzIqImtIzu", "created_at": {"$date": "2017-08-26T07:13:10Z"}, "favorites_count": 0, "user": {"screen_name": "salman0907", "name": "Salman Mithani", "id": "407417545", "friends": 249, "followers": 218, "verified": false, "account_created_at": {"$date": "2011-11-08T01:56:18Z"}, "location": "Sugar Land, TX", "description": "TAMU '19 \ud83d\udc4d\ud83c\udffd                                                 Instagram: @salman0907                             Snapchat: salman0907"}, "original_text": "Tornado Warning including Sugar Land TX, Pecan Grove TX, New Territory TX until 2:30 AM CDT https://t.co/nzIqImtIzu", "id2": "901341244319780864", "tweet_types": {"deleted_tweet": 0, "retweet": "901341244319780864", "quote_tweet": 0, "reply": 0, "original_tweet": 0}}, {"id": "901341707345809408", "text": "RT @NWSHouston: Tornado Warning including Sugar Land TX, Pecan Grove TX, New Territory TX until 2:30 AM CDT https://t.co/nzIqImtIzu", "created_at": {"$date": "2017-08-26T07:13:03Z"}, "favorites_count": 0, "user": {"screen_name": "rmarie717", "name": "Txrzel\u26be\ufe0f", "id": "820779079", "friends": 2583, "followers": 2586, "verified": false, "account_created_at": {"$date": "2012-09-13T02:52:19Z"}, "location": "Texas My Texas", "description": "Storm Chaser and meteorologist in my past life/ I can watch the weather channel for hours/ Jim Cantore retweeted me once  #weathergeek"}, "original_text": "Tornado Warning including Sugar Land TX, Pecan Grove TX, New Territory TX until 2:30 AM CDT https://t.co/nzIqImtIzu", "id2": "901341244319780864", "tweet_types": {"deleted_tweet": 0, "retweet": "901341244319780864", "quote_tweet": 0, "reply": 0, "original_tweet": 0}}, {"id": "901341855832391680", "text": "RT @NWSHouston: Tornado Warning including Sugar Land TX, Pecan Grove TX, New Territory TX until 2:30 AM CDT https://t.co/nzIqImtIzu", "created_at": {"$date": "2017-08-26T07:13:39Z"}, "favorites_count": 0, "user": {"screen_name": "Guardian_Elite", "name": "Guardian_Elite", "id": "199056422", "friends": 4997, "followers": 2423, "verified": false, "account_created_at": {"$date": "2010-10-05T22:50:20Z"}, "location": "Southern California", "description": "Single white female, 5' 6, light brown hair dyed auburn.  I love music.  I love sharing my most favorite songs that touch my heart and soul.  Love to laugh."}, "original_text": "Tornado Warning including Sugar Land TX, Pecan Grove TX, New Territory TX until 2:30 AM CDT https://t.co/nzIqImtIzu", "id2": "901341244319780864", "tweet_types": {"deleted_tweet": 0, "retweet": "901341244319780864", "quote_tweet": 0, "reply": 0, "original_tweet": 0}}, {"id": "901341898375352320", "text": "RT @NWSHouston: Tornado Warning including Sugar Land TX, Pecan Grove TX, New Territory TX until 2:30 AM CDT https://t.co/nzIqImtIzu", "created_at": {"$date": "2017-08-26T07:13:49Z"}, "favorites_count": 0, "user": {"screen_name": "yvngsavy", "name": "new new", "id": "2835415226", "friends": 909, "followers": 919, "verified": false, "account_created_at": {"$date": "2014-09-29T01:46:32Z"}, "location": "Richmond ", "description": "found what u was looking for \u00bf"}, "original_text": "Tornado Warning including Sugar Land TX, Pecan Grove TX, New Territory TX until 2:30 AM CDT https://t.co/nzIqImtIzu", "id2": "901341244319780864", "tweet_types": {"deleted_tweet": 0, "retweet": "901341244319780864", "quote_tweet": 0, "reply": 0, "original_tweet": 0}}, {"id": "901341766678401024", "text": "RT @NWSHouston: Tornado Warning including Sugar Land TX, Pecan Grove TX, New Territory TX until 2:30 AM CDT https://t.co/nzIqImtIzu", "created_at": {"$date": "2017-08-26T07:13:17Z"}, "favorites_count": 0, "user": {"screen_name": "rakeverm", "name": "Rakesh Verma", "id": "3049831782", "friends": 18, "followers": 5, "verified": false, "account_created_at": {"$date": "2015-02-28T13:54:21Z"}, "description": null}, "original_text": "Tornado Warning including Sugar Land TX, Pecan Grove TX, New Territory TX until 2:30 AM CDT https://t.co/nzIqImtIzu", "id2": "901341244319780864", "tweet_types": {"deleted_tweet": 0, "retweet": "901341244319780864", "quote_tweet": 0, "reply": 0, "original_tweet": 0}}, {"id": "901341948715257857", "text": "RT @NWSHouston: Tornado Warning including Sugar Land TX, Pecan Grove TX, New Territory TX until 2:30 AM CDT https://t.co/nzIqImtIzu", "created_at": {"$date": "2017-08-26T07:14:01Z"}, "favorites_count": 0, "user": {"screen_name": "QuitmanStephens", "name": "Quitman Stephens", "id": "557190047", "friends": 4831, "followers": 3220, "verified": false, "account_created_at": {"$date": "2012-04-18T20:25:42Z"}, "location": "Dallas and Fort Worth, Texas", "description": "Lawyer (#ERISA/employee benefits, exec comp & #health care. Passionate about @theBeatles & #fitness. Fluent in #French. @NYULaw @SMULawSchool & @SMU alum"}, "original_text": "Tornado Warning including Sugar Land TX, Pecan Grove TX, New Territory TX until 2:30 AM CDT https://t.co/nzIqImtIzu", "id2": "901341244319780864", "tweet_types": {"deleted_tweet": 0, "retweet": "901341244319780864", "quote_tweet": 0, "reply": 0, "original_tweet": 0}}, {"id": "901341954490945536", "text": "RT @NWSHouston: Tornado Warning including Sugar Land TX, Pecan Grove TX, New Territory TX until 2:30 AM CDT https://t.co/nzIqImtIzu", "created_at": {"$date": "2017-08-26T07:14:02Z"}, "favorites_count": 0, "user": {"screen_name": "desimerollinn", "name": "Alina", "id": "3297256111", "friends": 234, "followers": 130, "verified": false, "account_created_at": {"$date": "2015-07-27T08:43:23Z"}, "location": "HTX born ATL raised HTX livin.", "description": "they hatin'"}, "original_text": "Tornado Warning including Sugar Land TX, Pecan Grove TX, New Territory TX until 2:30 AM CDT https://t.co/nzIqImtIzu", "id2": "901341244319780864", "tweet_types": {"deleted_tweet": 0, "retweet": "901341244319780864", "quote_tweet": 0, "reply": 0, "original_tweet": 0}}, {"id": "901342121516556289", "text": "RT @NWSHouston: Tornado Warning including Sugar Land TX, Pecan Grove TX, New Territory TX until 2:30 AM CDT https://t.co/nzIqImtIzu", "created_at": {"$date": "2017-08-26T07:14:42Z"}, "favorites_count": 0, "user": {"screen_name": "ChrisLeeDallas", "name": "Chris Lee", "id": "62887698", "friends": 357, "followers": 85, "verified": false, "account_created_at": {"$date": "2009-08-04T18:20:29Z"}, "location": "Texas", "description": null}, "original_text": "Tornado Warning including Sugar Land TX, Pecan Grove TX, New Territory TX until 2:30 AM CDT https://t.co/nzIqImtIzu", "id2": "901341244319780864", "tweet_types": {"deleted_tweet": 0, "retweet": "901341244319780864", "quote_tweet": 0, "reply": 0, "original_tweet": 0}}, {"id": "901342038788124673", "text": "RT @NWSHouston: Tornado Warning including Sugar Land TX, Pecan Grove TX, New Territory TX until 2:30 AM CDT https://t.co/nzIqImtIzu", "created_at": {"$date": "2017-08-26T07:14:22Z"}, "favorites_count": 0, "user": {"screen_name": "Horus_Xero", "name": "HX", "id": "14427344", "friends": 2117, "followers": 910, "verified": false, "account_created_at": {"$date": "2008-04-17T23:45:56Z"}, "location": "Mo City/Houston, TX", "description": "Just don't lose your head around me. #Husband, #Father, #Gamer, #Sagittarius, #IAmStarCitizen, #MarvelHero & #Whovian. My methods are unorthodox, yet effective."}, "original_text": "Tornado Warning including Sugar Land TX, Pecan Grove TX, New Territory TX until 2:30 AM CDT https://t.co/nzIqImtIzu", "id2": "901341244319780864", "tweet_types": {"deleted_tweet": 0, "retweet": "901341244319780864", "quote_tweet": 0, "reply": 0, "original_tweet": 0}}, {"id": "901342105817186304", "text": "RT @NWSHouston: Tornado Warning including Sugar Land TX, Pecan Grove TX, New Territory TX until 2:30 AM CDT https://t.co/nzIqImtIzu", "created_at": {"$date": "2017-08-26T07:14:38Z"}, "favorites_count": 0, "user": {"screen_name": "JenniferReal04", "name": "Jennifer Real", "id": "64740675", "friends": 89, "followers": 24, "verified": false, "account_created_at": {"$date": "2009-08-11T15:22:08Z"}, "location": "Sugar Land, TX", "description": "I married the love of my life James 13 years ago and we have three children. Kaitlyn is 11, Austin is 8 and Savannah is 4. I love being a wife and mother!"}, "original_text": "Tornado Warning including Sugar Land TX, Pecan Grove TX, New Territory TX until 2:30 AM CDT https://t.co/nzIqImtIzu", "id2": "901341244319780864", "tweet_types": {"deleted_tweet": 0, "retweet": "901341244319780864", "quote_tweet": 0, "reply": 0, "original_tweet": 0}}, {"id": "901342402149060608", "text": "RT @NWSHouston: Tornado Warning including Sugar Land TX, Pecan Grove TX, New Territory TX until 2:30 AM CDT https://t.co/nzIqImtIzu", "created_at": {"$date": "2017-08-26T07:15:49Z"}, "favorites_count": 0, "user": {"screen_name": "hexogennotsugar", "name": "Cocytus", "id": "800154834422800384", "friends": 2561, "followers": 538, "verified": false, "account_created_at": {"$date": "2016-11-20T01:52:33Z"}, "location": "Texas", "description": "Flames on the side of my face. No lists. Putinists/RWNJ/LWNJ GTFO. #NeverMyPresident. #BenedictDonald. #StillWithHer. #GOPTreason.\ud83e\udd85"}, "original_text": "Tornado Warning including Sugar Land TX, Pecan Grove TX, New Territory TX until 2:30 AM CDT https://t.co/nzIqImtIzu", "id2": "901341244319780864", "tweet_types": {"deleted_tweet": 0, "retweet": "901341244319780864", "quote_tweet": 0, "reply": 0, "original_tweet": 0}}, {"id": "901342244833296384", "text": "RT @NWSHouston: Tornado Warning including Sugar Land TX, Pecan Grove TX, New Territory TX until 2:30 AM CDT https://t.co/nzIqImtIzu", "created_at": {"$date": "2017-08-26T07:15:11Z"}, "favorites_count": 0, "user": {"screen_name": "Heefosaurus", "name": "Heef \ud83c\udde8\ud83c\uddf1", "id": "275865761", "friends": 869, "followers": 1126, "verified": false, "account_created_at": {"$date": "2011-04-02T04:55:37Z"}, "location": "La Republica De Texas", "description": "If sincerely defending your beliefs is clearly and easily distinguishable from trolling then your beliefs are basic #ThugLife #ObeliskTwitter"}, "original_text": "Tornado Warning including Sugar Land TX, Pecan Grove TX, New Territory TX until 2:30 AM CDT https://t.co/nzIqImtIzu", "id2": "901341244319780864", "tweet_types": {"deleted_tweet": 0, "retweet": "901341244319780864", "quote_tweet": 0, "reply": 0, "original_tweet": 0}}, {"id": "901343044888408064", "text": "RT @NWSHouston: Tornado Warning including Sugar Land TX, Pecan Grove TX, New Territory TX until 2:30 AM CDT https://t.co/nzIqImtIzu", "created_at": {"$date": "2017-08-26T07:18:22Z"}, "favorites_count": 0, "user": {"screen_name": "anandb2k17", "name": "Anand Balasubramania", "id": "2374832432", "friends": 455, "followers": 91, "verified": false, "account_created_at": {"$date": "2014-03-06T04:56:44Z"}, "location": "Houston, TX", "description": "Certified Cloud Architect,  CoP CCOE Team\nCloud Adoption across the company using the leading Public (AWS) and Professional (Azure) Cloud Computing Systems"}, "original_text": "Tornado Warning including Sugar Land TX, Pecan Grove TX, New Territory TX until 2:30 AM CDT https://t.co/nzIqImtIzu", "id2": "901341244319780864", "tweet_types": {"deleted_tweet": 0, "retweet": "901341244319780864", "quote_tweet": 0, "reply": 0, "original_tweet": 0}}, {"id": "901343292469772288", "text": "RT @NWSHouston: Tornado Warning including Sugar Land TX, Pecan Grove TX, New Territory TX until 2:30 AM CDT https://t.co/nzIqImtIzu", "created_at": {"$date": "2017-08-26T07:19:21Z"}, "favorites_count": 0, "user": {"screen_name": "khaliyaaa__", "name": "melanistic princess", "id": "4549297152", "friends": 514, "followers": 640, "verified": false, "account_created_at": {"$date": "2015-12-13T18:19:13Z"}, "description": "Houston Texas"}, "original_text": "Tornado Warning including Sugar Land TX, Pecan Grove TX, New Territory TX until 2:30 AM CDT https://t.co/nzIqImtIzu", "id2": "901341244319780864", "tweet_types": {"deleted_tweet": 0, "retweet": "901341244319780864", "quote_tweet": 0, "reply": 0, "original_tweet": 0}}, {"id": "901371870460739584", "text": "RT @NWSHouston: Tornado Warning including Sugar Land TX, Pecan Grove TX, New Territory TX until 2:30 AM CDT https://t.co/nzIqImtIzu", "created_at": {"$date": "2017-08-26T09:12:55Z"}, "favorites_count": 0, "user": {"screen_name": "tomwoods55", "name": "Tom Woods", "id": "120146232", "friends": 15437, "followers": 15654, "verified": false, "account_created_at": {"$date": "2010-03-05T16:09:43Z"}, "location": "Largo, Florida", "description": "#MAGA #Vet #Molon-Labe #Christian #BAN-MSM #ANTI-PC #Karatbars Invest Secure Easy Affiliates  http://goo.gl/bVkn5 \n      #Alignable http://www.goo.gl/FXyCqj"}, "original_text": "Tornado Warning including Sugar Land TX, Pecan Grove TX, New Territory TX until 2:30 AM CDT https://t.co/nzIqImtIzu", "id2": "901341244319780864", "tweet_types": {"deleted_tweet": 0, "retweet": "901341244319780864", "quote_tweet": 0, "reply": 0, "original_tweet": 0}}, {"id": "901355828816609280", "text": "RT @NWSHouston: Tornado Warning including Sugar Land TX, Pecan Grove TX, New Territory TX until 2:30 AM CDT https://t.co/nzIqImtIzu", "created_at": {"$date": "2017-08-26T08:09:10Z"}, "favorites_count": 0, "user": {"screen_name": "ja8208", "name": "Jennifer Anderson", "id": "537442024", "friends": 55, "followers": 20, "verified": false, "account_created_at": {"$date": "2012-03-26T18:23:07Z"}, "location": "Redmond, WA", "description": null}, "original_text": "Tornado Warning including Sugar Land TX, Pecan Grove TX, New Territory TX until 2:30 AM CDT https://t.co/nzIqImtIzu", "id2": "901341244319780864", "tweet_types": {"deleted_tweet": 0, "retweet": "901341244319780864", "quote_tweet": 0, "reply": 0, "original_tweet": 0}}, {"id": "901351119221379072", "text": "RT @NWSHouston: Tornado Warning including Sugar Land TX, Pecan Grove TX, New Territory TX until 2:30 AM CDT https://t.co/nzIqImtIzu", "created_at": {"$date": "2017-08-26T07:50:27Z"}, "favorites_count": 0, "user": {"screen_name": "ThomasDetron", "name": "murdline DK \ud83c\udfc0\u3299\ufe0f", "id": "891385969147904000", "friends": 419, "followers": 40, "verified": false, "account_created_at": {"$date": "2017-07-29T19:52:31Z"}, "location": "At the table \ud83c\udfc0\ud83c\udf7d", "description": "I Can do all things though Christ \ud83d\ude4f\ud83c\udffd Philip 4:13 Murda every defender \u26b0\ufe0f\ud83d\udcb8"}, "original_text": "Tornado Warning including Sugar Land TX, Pecan Grove TX, New Territory TX until 2:30 AM CDT https://t.co/nzIqImtIzu", "id2": "901341244319780864", "tweet_types": {"deleted_tweet": 0, "retweet": "901341244319780864", "quote_tweet": 0, "reply": 0, "original_tweet": 0}}, {"id": "901352599986868224", "text": "RT @NWSHouston: Tornado Warning including Sugar Land TX, Pecan Grove TX, New Territory TX until 2:30 AM CDT https://t.co/nzIqImtIzu", "created_at": {"$date": "2017-08-26T07:56:20Z"}, "favorites_count": 0, "user": {"screen_name": "Nabiha01", "name": "nabihaa", "id": "1535855262", "friends": 227, "followers": 184, "verified": false, "account_created_at": {"$date": "2013-06-21T06:28:45Z"}, "location": "Houston, TX", "description": "ayyeee wus good"}, "original_text": "Tornado Warning including Sugar Land TX, Pecan Grove TX, New Territory TX until 2:30 AM CDT https://t.co/nzIqImtIzu", "id2": "901341244319780864", "tweet_types": {"deleted_tweet": 0, "retweet": "901341244319780864", "quote_tweet": 0, "reply": 0, "original_tweet": 0}}, {"id": "901352993773236224", "text": "RT @NWSHouston: Tornado Warning including Sugar Land TX, Pecan Grove TX, New Territory TX until 2:30 AM CDT https://t.co/nzIqImtIzu", "created_at": {"$date": "2017-08-26T07:57:54Z"}, "favorites_count": 0, "user": {"screen_name": "IMSOJANJUA", "name": "\u0641\u0631\u062d\u0627\u0646", "id": "276422239", "friends": 391, "followers": 555, "verified": false, "account_created_at": {"$date": "2011-04-03T09:53:04Z"}, "location": "Bringing Canada to Texas ", "description": "\"It'll all work out. it always does.\""}, "original_text": "Tornado Warning including Sugar Land TX, Pecan Grove TX, New Territory TX until 2:30 AM CDT https://t.co/nzIqImtIzu", "id2": "901341244319780864", "tweet_types": {"deleted_tweet": 0, "retweet": "901341244319780864", "quote_tweet": 0, "reply": 0, "original_tweet": 0}}, {"id": "901353117404581888", "text": "RT @NWSHouston: Tornado Warning including Sugar Land TX, Pecan Grove TX, New Territory TX until 2:30 AM CDT https://t.co/nzIqImtIzu", "created_at": {"$date": "2017-08-26T07:58:24Z"}, "favorites_count": 0, "user": {"screen_name": "StieberIns", "name": "Stieber Insurance", "id": "317996147", "friends": 73, "followers": 50, "verified": false, "account_created_at": {"$date": "2011-06-15T20:07:48Z"}, "location": "Richmond, TX; Fulshear, TX", "description": "Stieber Ins are an independent insurance agency in Texas.  We manage home, auto, motorcycle, life, health insurance and so much more."}, "original_text": "Tornado Warning including Sugar Land TX, Pecan Grove TX, New Territory TX until 2:30 AM CDT https://t.co/nzIqImtIzu", "id2": "901341244319780864", "tweet_types": {"deleted_tweet": 0, "retweet": "901341244319780864", "quote_tweet": 0, "reply": 0, "original_tweet": 0}}, {"id": "901564775318073345", "text": "RT @NWSHouston: Tornado Warning including Sugar Land TX, Pecan Grove TX, New Territory TX until 2:30 AM CDT https://t.co/nzIqImtIzu", "created_at": {"$date": "2017-08-26T21:59:27Z"}, "favorites_count": 0, "user": {"screen_name": "zeb_CR", "name": "Zeb", "id": "773148316834025472", "friends": 53, "followers": 68, "verified": false, "account_created_at": {"$date": "2016-09-06T13:18:17Z"}, "description": null}, "original_text": "Tornado Warning including Sugar Land TX, Pecan Grove TX, New Territory TX until 2:30 AM CDT https://t.co/nzIqImtIzu", "id2": "901341244319780864", "tweet_types": {"deleted_tweet": 0, "retweet": "901341244319780864", "quote_tweet": 0, "reply": 0, "original_tweet": 0}}, {"id": "901391452542054400", "text": "RT @NWSHouston: Tornado Warning including Sugar Land TX, Pecan Grove TX, New Territory TX until 2:30 AM CDT https://t.co/nzIqImtIzu", "created_at": {"$date": "2017-08-26T10:30:43Z"}, "favorites_count": 0, "user": {"screen_name": "McBubberz", "name": "McBubberz", "id": "1892275255", "friends": 4915, "followers": 925, "verified": false, "account_created_at": {"$date": "2013-09-22T02:52:30Z"}, "location": "United States", "description": null}, "original_text": "Tornado Warning including Sugar Land TX, Pecan Grove TX, New Territory TX until 2:30 AM CDT https://t.co/nzIqImtIzu", "id2": "901341244319780864", "tweet_types": {"deleted_tweet": 0, "retweet": "901341244319780864", "quote_tweet": 0, "reply": 0, "original_tweet": 0}}, {"id": "901370713281527809", "text": "RT @NWSHouston: Tornado Warning including Sugar Land TX, Pecan Grove TX, New Territory TX until 2:30 AM CDT https://t.co/nzIqImtIzu", "created_at": {"$date": "2017-08-26T09:08:19Z"}, "favorites_count": 0, "user": {"screen_name": "Elizabeth76642", "name": "Elizabeth McDaniel", "id": "835089542172401664", "friends": 371, "followers": 61, "verified": false, "account_created_at": {"$date": "2017-02-24T11:30:36Z"}, "location": "Groesbeck, TX", "description": "Full time retired teacher, Storm-spotter, birder, storyteller, Master Naturalist, DoTerraEssential oils"}, "original_text": "Tornado Warning including Sugar Land TX, Pecan Grove TX, New Territory TX until 2:30 AM CDT https://t.co/nzIqImtIzu", "id2": "901341244319780864", "tweet_types": {"deleted_tweet": 0, "retweet": "901341244319780864", "quote_tweet": 0, "reply": 0, "original_tweet": 0}}, {"id": "901346432703242240", "text": "RT @NWSHouston: Tornado Warning including Sugar Land TX, Pecan Grove TX, New Territory TX until 2:30 AM CDT https://t.co/nzIqImtIzu", "created_at": {"$date": "2017-08-26T07:31:50Z"}, "favorites_count": 0, "user": {"screen_name": "mshei1824", "name": "Mekyle Sheikh", "id": "2616431520", "friends": 972, "followers": 1428, "verified": false, "account_created_at": {"$date": "2014-07-11T01:05:41Z"}, "location": "Sugar Land, TX", "description": "UH Engineering 2020"}, "original_text": "Tornado Warning including Sugar Land TX, Pecan Grove TX, New Territory TX until 2:30 AM CDT https://t.co/nzIqImtIzu", "id2": "901341244319780864", "tweet_types": {"deleted_tweet": 0, "retweet": "901341244319780864", "quote_tweet": 0, "reply": 0, "original_tweet": 0}}, {"id": "901346719505543168", "text": "RT @NWSHouston: Tornado Warning including Sugar Land TX, Pecan Grove TX, New Territory TX until 2:30 AM CDT https://t.co/nzIqImtIzu", "created_at": {"$date": "2017-08-26T07:32:58Z"}, "favorites_count": 0, "user": {"screen_name": "raj13ali", "name": "Raj Ali", "id": "2720524208", "friends": 266, "followers": 458, "verified": false, "account_created_at": {"$date": "2014-08-10T01:17:41Z"}, "location": "Houston, TX", "description": "Sc: rajali3"}, "original_text": "Tornado Warning including Sugar Land TX, Pecan Grove TX, New Territory TX until 2:30 AM CDT https://t.co/nzIqImtIzu", "id2": "901341244319780864", "tweet_types": {"deleted_tweet": 0, "retweet": "901341244319780864", "quote_tweet": 0, "reply": 0, "original_tweet": 0}}, {"id": "901346973915238400", "text": "RT @NWSHouston: Tornado Warning including Sugar Land TX, Pecan Grove TX, New Territory TX until 2:30 AM CDT https://t.co/nzIqImtIzu", "created_at": {"$date": "2017-08-26T07:33:59Z"}, "favorites_count": 0, "user": {"screen_name": "ManticeComm", "name": "MANTICE COMM", "id": "821598087370199047", "friends": 34, "followers": 4, "verified": false, "account_created_at": {"$date": "2017-01-18T06:00:23Z"}, "location": "Texas, USA", "description": "A company dedicated in striving for success and perfection while working towards making it customers feel like a part of a family. #STSA"}, "original_text": "Tornado Warning including Sugar Land TX, Pecan Grove TX, New Territory TX until 2:30 AM CDT https://t.co/nzIqImtIzu", "id2": "901341244319780864", "tweet_types": {"deleted_tweet": 0, "retweet": "901341244319780864", "quote_tweet": 0, "reply": 0, "original_tweet": 0}}, {"id": "901347113707200512", "text": "RT @NWSHouston: Tornado Warning including Sugar Land TX, Pecan Grove TX, New Territory TX until 2:30 AM CDT https://t.co/nzIqImtIzu", "created_at": {"$date": "2017-08-26T07:34:32Z"}, "favorites_count": 0, "user": {"screen_name": "Neha_A_", "name": "neha", "id": "2707974446", "friends": 448, "followers": 672, "verified": false, "account_created_at": {"$date": "2014-08-05T01:49:04Z"}, "location": "Houston, TX", "description": "just appreciating life's vibe"}, "original_text": "Tornado Warning including Sugar Land TX, Pecan Grove TX, New Territory TX until 2:30 AM CDT https://t.co/nzIqImtIzu", "id2": "901341244319780864", "tweet_types": {"deleted_tweet": 0, "retweet": "901341244319780864", "quote_tweet": 0, "reply": 0, "original_tweet": 0}}, {"id": "901347048070557696", "text": "RT @NWSHouston: Tornado Warning including Sugar Land TX, Pecan Grove TX, New Territory TX until 2:30 AM CDT https://t.co/nzIqImtIzu", "created_at": {"$date": "2017-08-26T07:34:17Z"}, "favorites_count": 0, "user": {"screen_name": "FilsARek", "name": "PictoChat", "id": "3631844240", "friends": 236, "followers": 114, "verified": false, "account_created_at": {"$date": "2015-09-20T23:36:25Z"}, "location": "United States", "description": "Games, art, and memes galore. Find my mods on GameBanana or on Discord."}, "original_text": "Tornado Warning including Sugar Land TX, Pecan Grove TX, New Territory TX until 2:30 AM CDT https://t.co/nzIqImtIzu", "id2": "901341244319780864", "tweet_types": {"deleted_tweet": 0, "retweet": "901341244319780864", "quote_tweet": 0, "reply": 0, "original_tweet": 0}}]