[{"id": "901364559021322240", "text": "RT @NWSCorpus: Aviso de Inundaci\u00f3n Repentina contin\u00faa Portland TX, Ingleside TX, Rockport TX hasta las 6:45 AM CDT https://t.co/kuQICWhRH9", "created_at": {"$date": "2017-08-26T08:43:52Z"}, "favorites_count": 0, "user": {"screen_name": "RealSrDollar_", "name": "Sr.Dollar", "id": "726960078859976704", "friends": 5000, "followers": 3679, "verified": false, "account_created_at": {"$date": "2016-05-02T02:22:43Z"}, "location": "Washington, DC", "description": "Former Owner of /Dollar Services/Dollar & Associates/Former Vendor  to Family Dollar Inc / \u062e\u062f\u0645\u0627\u062a \u0627\u0644\u0623\u0645\u0646 \u0627\u0644\u062f\u0648\u0644\u0627\u0631 /Pastor / Official account of   Sr.Dollar"}, "original_text": "Aviso de Inundaci\u00f3n Repentina contin\u00faa Portland TX, Ingleside TX, Rockport TX hasta las 6:45 AM CDT https://t.co/kuQICWhRH9", "id2": "901351728305537024", "tweet_types": {"deleted_tweet": 0, "retweet": "901351728305537024", "quote_tweet": 0, "reply": 0, "original_tweet": 0}}, {"id": "901353925357563904", "text": "RT @NWSCorpus: Aviso de Inundaci\u00f3n Repentina contin\u00faa Portland TX, Ingleside TX, Rockport TX hasta las 6:45 AM CDT https://t.co/kuQICWhRH9", "created_at": {"$date": "2017-08-26T08:01:36Z"}, "favorites_count": 0, "user": {"screen_name": "MakingTownsGuy", "name": "#1 Traveling Fan!!", "id": "16075168", "friends": 1998, "followers": 994, "verified": false, "account_created_at": {"$date": "2008-09-01T02:29:32Z"}, "location": "Dallas, TX", "description": "Big Indy wrestling fan. Co-owns @TheMTclassic with @MikeHales9 I work for @CanuckPro I attend shows all over the world. #1 traveling fan! Dual citizen \ud83c\uddfa\ud83c\uddf8 \ud83c\udde8\ud83c\udde6"}, "original_text": "Aviso de Inundaci\u00f3n Repentina contin\u00faa Portland TX, Ingleside TX, Rockport TX hasta las 6:45 AM CDT https://t.co/kuQICWhRH9", "id2": "901351728305537024", "tweet_types": {"deleted_tweet": 0, "retweet": "901351728305537024", "quote_tweet": 0, "reply": 0, "original_tweet": 0}}, {"id": "901354198075420673", "text": "RT @NWSCorpus: Aviso de Inundaci\u00f3n Repentina contin\u00faa Portland TX, Ingleside TX, Rockport TX hasta las 6:45 AM CDT https://t.co/kuQICWhRH9", "created_at": {"$date": "2017-08-26T08:02:41Z"}, "favorites_count": 0, "user": {"screen_name": "StormWchAmerica", "name": "Storm Watch America", "id": "636484224", "friends": 886, "followers": 1514, "verified": false, "account_created_at": {"$date": "2012-07-15T19:36:54Z"}, "location": "America", "description": "Coverage of severe weather across America with live severe storm & tornado watches & warnings! Plus, hurricane coverage! Apart of @channel1network"}, "original_text": "Aviso de Inundaci\u00f3n Repentina contin\u00faa Portland TX, Ingleside TX, Rockport TX hasta las 6:45 AM CDT https://t.co/kuQICWhRH9", "id2": "901351728305537024", "tweet_types": {"deleted_tweet": 0, "retweet": "901351728305537024", "quote_tweet": 0, "reply": 0, "original_tweet": 0}}, {"id": "901354786112454656", "text": "RT @NWSCorpus: Aviso de Inundaci\u00f3n Repentina contin\u00faa Portland TX, Ingleside TX, Rockport TX hasta las 6:45 AM CDT https://t.co/kuQICWhRH9", "created_at": {"$date": "2017-08-26T08:05:02Z"}, "favorites_count": 0, "user": {"screen_name": "pedromateran", "name": "Ped&Pet \ud83d\udc7d\ud83d\udd46\ud83d\udd49\u264f", "id": "220484220", "friends": 675, "followers": 394, "verified": false, "account_created_at": {"$date": "2010-11-27T22:58:34Z"}, "location": "Chandler, AZ", "description": "Motivador, Evolucionista Espiritual, Economist, amante de los viajes y la astrolog\u00eda"}, "original_text": "Aviso de Inundaci\u00f3n Repentina contin\u00faa Portland TX, Ingleside TX, Rockport TX hasta las 6:45 AM CDT https://t.co/kuQICWhRH9", "id2": "901351728305537024", "tweet_types": {"deleted_tweet": 0, "retweet": "901351728305537024", "quote_tweet": 0, "reply": 0, "original_tweet": 0}}, {"id": "901355510359875584", "text": "RT @NWSCorpus: Aviso de Inundaci\u00f3n Repentina contin\u00faa Portland TX, Ingleside TX, Rockport TX hasta las 6:45 AM CDT https://t.co/kuQICWhRH9", "created_at": {"$date": "2017-08-26T08:07:54Z"}, "favorites_count": 0, "user": {"screen_name": "Monalisazelf", "name": "Mona vanderSmitte \ud83d\uddbc", "id": "92511984", "friends": 4065, "followers": 1466, "verified": false, "account_created_at": {"$date": "2009-11-25T12:34:49Z"}, "description": "Twitterbirdwatcher\nLearning all the time\nRetweets and links are not (ipso facto) endorsements"}, "original_text": "Aviso de Inundaci\u00f3n Repentina contin\u00faa Portland TX, Ingleside TX, Rockport TX hasta las 6:45 AM CDT https://t.co/kuQICWhRH9", "id2": "901351728305537024", "tweet_types": {"deleted_tweet": 0, "retweet": "901351728305537024", "quote_tweet": 0, "reply": 0, "original_tweet": 0}}, {"id": "901351797717184512", "text": "RT @NWSCorpus: Aviso de Inundaci\u00f3n Repentina contin\u00faa Portland TX, Ingleside TX, Rockport TX hasta las 6:45 AM CDT https://t.co/kuQICWhRH9", "created_at": {"$date": "2017-08-26T07:53:09Z"}, "favorites_count": 0, "user": {"screen_name": "twright55", "name": "Tatiana Wright", "id": "93288759", "friends": 808, "followers": 9621, "verified": false, "account_created_at": {"$date": "2009-11-29T00:17:35Z"}, "location": "Tysons Corner, VA", "description": "I am just #Tatiana, #Republican. The Politician. Proud American. #MAGA #AmericaFirst"}, "original_text": "Aviso de Inundaci\u00f3n Repentina contin\u00faa Portland TX, Ingleside TX, Rockport TX hasta las 6:45 AM CDT https://t.co/kuQICWhRH9", "id2": "901351728305537024", "tweet_types": {"deleted_tweet": 0, "retweet": "901351728305537024", "quote_tweet": 0, "reply": 0, "original_tweet": 0}}, {"id": "901363367746707456", "text": "RT @NWSCorpus: Aviso de Inundaci\u00f3n Repentina contin\u00faa Portland TX, Ingleside TX, Rockport TX hasta las 6:45 AM CDT https://t.co/kuQICWhRH9", "created_at": {"$date": "2017-08-26T08:39:08Z"}, "favorites_count": 0, "user": {"screen_name": "BeeNewsDaily", "name": "BeeNewsDaily", "id": "853736260397084674", "friends": 2855, "followers": 1043, "verified": false, "account_created_at": {"$date": "2017-04-16T22:26:00Z"}, "location": "Washington, DC", "description": "BeeNewsDaily provides investigative reporting, in-depth national political coverage, national security news, opinion, sports and more. Post your own news here."}, "original_text": "Aviso de Inundaci\u00f3n Repentina contin\u00faa Portland TX, Ingleside TX, Rockport TX hasta las 6:45 AM CDT https://t.co/kuQICWhRH9", "id2": "901351728305537024", "tweet_types": {"deleted_tweet": 0, "retweet": "901351728305537024", "quote_tweet": 0, "reply": 0, "original_tweet": 0}}]