[{"id": "901568716453838850", "text": "RT @TxStormChasers: 8/26 1022AM: Simulated radar from HRRR through this evening. Life-threatening flooding risk in SE TX - including HO\u2026 ", "created_at": {"$date": "2017-08-26T22:15:06Z"}, "favorites_count": 0, "user": {"screen_name": "curtina15", "name": "Curtina Wilson", "id": "3193717926", "friends": 150, "followers": 20, "verified": false, "account_created_at": {"$date": "2015-05-13T00:59:07Z"}, "location": "Arlington, TX", "description": null}, "original_text": "8/26 1022AM: Simulated radar from HRRR through this evening. Life-threatening flooding risk in SE TX - including HO\u2026 https://t.co/0jX4EZ23N5", "id2": "901464954989162497", "tweet_types": {"deleted_tweet": 0, "retweet": "901464954989162497", "quote_tweet": 0, "reply": 0, "original_tweet": 0}}, {"id": "901477900414853121", "text": "RT @TxStormChasers: 8/26 1022AM: Simulated radar from HRRR through this evening. Life-threatening flooding risk in SE TX - including HO\u2026 ", "created_at": {"$date": "2017-08-26T16:14:14Z"}, "favorites_count": 0, "user": {"screen_name": "guevara_gaby02", "name": "Gabriela Guevara", "id": "580494985", "friends": 181, "followers": 84, "verified": false, "account_created_at": {"$date": "2012-05-15T03:18:28Z"}, "location": "Houston, Texas (USA)", "description": null}, "original_text": "8/26 1022AM: Simulated radar from HRRR through this evening. Life-threatening flooding risk in SE TX - including HO\u2026 https://t.co/0jX4EZ23N5", "id2": "901464954989162497", "tweet_types": {"deleted_tweet": 0, "retweet": "901464954989162497", "quote_tweet": 0, "reply": 0, "original_tweet": 0}}, {"id": "901478626763448323", "text": "RT @TxStormChasers: 8/26 1022AM: Simulated radar from HRRR through this evening. Life-threatening flooding risk in SE TX - including HO\u2026 ", "created_at": {"$date": "2017-08-26T16:17:07Z"}, "favorites_count": 0, "user": {"screen_name": "inkjoy", "name": "Ty Simsak", "id": "25008185", "friends": 827, "followers": 63, "verified": false, "account_created_at": {"$date": "2009-03-18T02:16:38Z"}, "description": "Another member of the resistance fighting the good fight"}, "original_text": "8/26 1022AM: Simulated radar from HRRR through this evening. Life-threatening flooding risk in SE TX - including HO\u2026 https://t.co/0jX4EZ23N5", "id2": "901464954989162497", "tweet_types": {"deleted_tweet": 0, "retweet": "901464954989162497", "quote_tweet": 0, "reply": 0, "original_tweet": 0}}, {"id": "901467253694189569", "text": "RT @TxStormChasers: 8/26 1022AM: Simulated radar from HRRR through this evening. Life-threatening flooding risk in SE TX - including HO\u2026 ", "created_at": {"$date": "2017-08-26T15:31:56Z"}, "favorites_count": 0, "user": {"screen_name": "MarianaPinedaBU", "name": "Mariana Pineda", "id": "578590676", "friends": 346, "followers": 2156, "verified": false, "account_created_at": {"$date": "2012-05-13T02:53:31Z"}, "location": "Houston/ Mexico City", "description": "Emmy award-winning bilingual journalist\u2022 #NewsReporter\u2022 #Writer for @Contently\u2022 #Runner\u2022#Wife\u2022#Mom\u2022#DogMom\u2022and\u2022a proud @Baylor Bear who loves God"}, "original_text": "8/26 1022AM: Simulated radar from HRRR through this evening. Life-threatening flooding risk in SE TX - including HO\u2026 https://t.co/0jX4EZ23N5", "id2": "901464954989162497", "tweet_types": {"deleted_tweet": 0, "retweet": "901464954989162497", "quote_tweet": 0, "reply": 0, "original_tweet": 0}}, {"id": "901467356450484224", "text": "RT @TxStormChasers: 8/26 1022AM: Simulated radar from HRRR through this evening. Life-threatening flooding risk in SE TX - including HO\u2026 ", "created_at": {"$date": "2017-08-26T15:32:20Z"}, "favorites_count": 0, "user": {"screen_name": "meosha", "name": "meosha", "id": "18799027", "friends": 402, "followers": 112, "verified": false, "account_created_at": {"$date": "2009-01-09T11:41:04Z"}, "location": "Texas", "description": null}, "original_text": "8/26 1022AM: Simulated radar from HRRR through this evening. Life-threatening flooding risk in SE TX - including HO\u2026 https://t.co/0jX4EZ23N5", "id2": "901464954989162497", "tweet_types": {"deleted_tweet": 0, "retweet": "901464954989162497", "quote_tweet": 0, "reply": 0, "original_tweet": 0}}, {"id": "901467978348326912", "text": "RT @TxStormChasers: 8/26 1022AM: Simulated radar from HRRR through this evening. Life-threatening flooding risk in SE TX - including HO\u2026 ", "created_at": {"$date": "2017-08-26T15:34:49Z"}, "favorites_count": 0, "user": {"screen_name": "rmatwick", "name": "Rob Matwick", "id": "2990199901", "friends": 419, "followers": 479, "verified": false, "account_created_at": {"$date": "2015-01-19T17:25:12Z"}, "location": "Southlake, Texas", "description": "Executive VP, Business Operations, Texas Rangers. University of South Carolina grad. Proud husband and SL Carroll Emerald Belle dad. Native of McKeesport, PA."}, "original_text": "8/26 1022AM: Simulated radar from HRRR through this evening. Life-threatening flooding risk in SE TX - including HO\u2026 https://t.co/0jX4EZ23N5", "id2": "901464954989162497", "tweet_types": {"deleted_tweet": 0, "retweet": "901464954989162497", "quote_tweet": 0, "reply": 0, "original_tweet": 0}}, {"id": "901467854154944512", "text": "RT @TxStormChasers: 8/26 1022AM: Simulated radar from HRRR through this evening. Life-threatening flooding risk in SE TX - including HO\u2026 ", "created_at": {"$date": "2017-08-26T15:34:19Z"}, "favorites_count": 0, "user": {"screen_name": "SaraBeth_Hope", "name": "SaraBeth", "id": "16150686", "friends": 338, "followers": 147, "verified": false, "account_created_at": {"$date": "2008-09-05T22:37:54Z"}, "location": " Houston, TX", "description": "Life's better outside"}, "original_text": "8/26 1022AM: Simulated radar from HRRR through this evening. Life-threatening flooding risk in SE TX - including HO\u2026 https://t.co/0jX4EZ23N5", "id2": "901464954989162497", "tweet_types": {"deleted_tweet": 0, "retweet": "901464954989162497", "quote_tweet": 0, "reply": 0, "original_tweet": 0}}, {"id": "901469306210406400", "text": "RT @TxStormChasers: 8/26 1022AM: Simulated radar from HRRR through this evening. Life-threatening flooding risk in SE TX - including HO\u2026 ", "created_at": {"$date": "2017-08-26T15:40:05Z"}, "favorites_count": 0, "user": {"screen_name": "amandadavis222", "name": "AMANDA WILLOWS", "id": "421614720", "friends": 299, "followers": 155, "verified": false, "account_created_at": {"$date": "2011-11-26T05:10:22Z"}, "location": "Reno, TX", "description": "Happily married mother of two and proud grandmother."}, "original_text": "8/26 1022AM: Simulated radar from HRRR through this evening. Life-threatening flooding risk in SE TX - including HO\u2026 https://t.co/0jX4EZ23N5", "id2": "901464954989162497", "tweet_types": {"deleted_tweet": 0, "retweet": "901464954989162497", "quote_tweet": 0, "reply": 0, "original_tweet": 0}}, {"id": "901469597710397441", "text": "RT @TxStormChasers: 8/26 1022AM: Simulated radar from HRRR through this evening. Life-threatening flooding risk in SE TX - including HO\u2026 ", "created_at": {"$date": "2017-08-26T15:41:15Z"}, "favorites_count": 0, "user": {"screen_name": "KarinaFRamirez", "name": "Karina Ram\u00edrez", "id": "17087240", "friends": 1161, "followers": 1671, "verified": true, "account_created_at": {"$date": "2008-10-31T16:11:17Z"}, "location": "United States", "description": "Independent #journo, former @aldiadallas/@DallasNews, @AmericanUAlum, #ecuador #fanoftheplanet"}, "original_text": "8/26 1022AM: Simulated radar from HRRR through this evening. Life-threatening flooding risk in SE TX - including HO\u2026 https://t.co/0jX4EZ23N5", "id2": "901464954989162497", "tweet_types": {"deleted_tweet": 0, "retweet": "901464954989162497", "quote_tweet": 0, "reply": 0, "original_tweet": 0}}, {"id": "901470517860995072", "text": "RT @TxStormChasers: 8/26 1022AM: Simulated radar from HRRR through this evening. Life-threatening flooding risk in SE TX - including HO\u2026 ", "created_at": {"$date": "2017-08-26T15:44:54Z"}, "favorites_count": 0, "user": {"screen_name": "TVPromoGuy", "name": "Gary Thomas Wann", "id": "29804665", "friends": 4056, "followers": 4294, "verified": false, "account_created_at": {"$date": "2009-04-08T19:59:27Z"}, "location": "Dallas, TX USA", "description": "Happily Married with 4 Kids | VP, Brand Marketing @ NBC | Purveyor of Fine Promos | Advertising Scientist | Graduate Student @ Texas A&M University | https://t.co/ikP1jhGmS0"}, "original_text": "8/26 1022AM: Simulated radar from HRRR through this evening. Life-threatening flooding risk in SE TX - including HO\u2026 https://t.co/0jX4EZ23N5", "id2": "901464954989162497", "tweet_types": {"deleted_tweet": 0, "retweet": "901464954989162497", "quote_tweet": 0, "reply": 0, "original_tweet": 0}}, {"id": "901470402651840512", "text": "RT @TxStormChasers: 8/26 1022AM: Simulated radar from HRRR through this evening. Life-threatening flooding risk in SE TX - including HO\u2026 ", "created_at": {"$date": "2017-08-26T15:44:27Z"}, "favorites_count": 0, "user": {"screen_name": "JonRMcClure", "name": "Jon McClure", "id": "466066119", "friends": 859, "followers": 861, "verified": true, "account_created_at": {"$date": "2012-01-17T01:16:46Z"}, "location": "Washington, DC", "description": "Interactive news editor @politico. Previously, @dallasnews, @TheDetailTV, @mujschool, @UniFAU, @KUEnglish. Kansas City kid."}, "original_text": "8/26 1022AM: Simulated radar from HRRR through this evening. Life-threatening flooding risk in SE TX - including HO\u2026 https://t.co/0jX4EZ23N5", "id2": "901464954989162497", "tweet_types": {"deleted_tweet": 0, "retweet": "901464954989162497", "quote_tweet": 0, "reply": 0, "original_tweet": 0}}, {"id": "901470804776505344", "text": "RT @TxStormChasers: 8/26 1022AM: Simulated radar from HRRR through this evening. Life-threatening flooding risk in SE TX - including HO\u2026 ", "created_at": {"$date": "2017-08-26T15:46:03Z"}, "favorites_count": 0, "user": {"screen_name": "txagmbelcher", "name": "Matt Belcher", "id": "617586415", "friends": 53, "followers": 13, "verified": false, "account_created_at": {"$date": "2012-06-24T23:47:27Z"}, "description": null}, "original_text": "8/26 1022AM: Simulated radar from HRRR through this evening. Life-threatening flooding risk in SE TX - including HO\u2026 https://t.co/0jX4EZ23N5", "id2": "901464954989162497", "tweet_types": {"deleted_tweet": 0, "retweet": "901464954989162497", "quote_tweet": 0, "reply": 0, "original_tweet": 0}}, {"id": "901471131064041472", "text": "RT @TxStormChasers: 8/26 1022AM: Simulated radar from HRRR through this evening. Life-threatening flooding risk in SE TX - including HO\u2026 ", "created_at": {"$date": "2017-08-26T15:47:20Z"}, "favorites_count": 0, "user": {"screen_name": "NtxWeatherDepo", "name": "NtxWeatherDepo", "id": "2319202761", "friends": 34, "followers": 187, "verified": false, "account_created_at": {"$date": "2014-02-02T02:35:21Z"}, "location": "North Texas ", "description": "Latest updates/forecasts"}, "original_text": "8/26 1022AM: Simulated radar from HRRR through this evening. Life-threatening flooding risk in SE TX - including HO\u2026 https://t.co/0jX4EZ23N5", "id2": "901464954989162497", "tweet_types": {"deleted_tweet": 0, "retweet": "901464954989162497", "quote_tweet": 0, "reply": 0, "original_tweet": 0}}, {"id": "901471912441901056", "text": "RT @TxStormChasers: 8/26 1022AM: Simulated radar from HRRR through this evening. Life-threatening flooding risk in SE TX - including HO\u2026 ", "created_at": {"$date": "2017-08-26T15:50:27Z"}, "favorites_count": 0, "user": {"screen_name": "AluminumCloud", "name": "Debra Kusek", "id": "23197116", "friends": 441, "followers": 644, "verified": false, "account_created_at": {"$date": "2009-03-07T14:35:56Z"}, "location": "Dallas, TX", "description": "Wife, band mom, leader at Southwest Airlines University. Lover of relaxation, food, and the window seat. My tweets are my own, not those of SWA or any company."}, "original_text": "8/26 1022AM: Simulated radar from HRRR through this evening. Life-threatening flooding risk in SE TX - including HO\u2026 https://t.co/0jX4EZ23N5", "id2": "901464954989162497", "tweet_types": {"deleted_tweet": 0, "retweet": "901464954989162497", "quote_tweet": 0, "reply": 0, "original_tweet": 0}}, {"id": "901472211902631936", "text": "RT @TxStormChasers: 8/26 1022AM: Simulated radar from HRRR through this evening. Life-threatening flooding risk in SE TX - including HO\u2026 ", "created_at": {"$date": "2017-08-26T15:51:38Z"}, "favorites_count": 0, "user": {"screen_name": "Julie_Elwood", "name": "Julie Elwood", "id": "272622786", "friends": 347, "followers": 709, "verified": false, "account_created_at": {"$date": "2011-03-26T21:16:12Z"}, "location": "East Texas", "description": "I'm just Julie. Crazy Cat Lady, animal lover, fan of Ghost Adventures, GOT, TWD, traveler, shopper, and foodie. \ud83d\udc31\ud83d\udc08\ud83d\udc3e\ud83d\udc36\ud83d\udc15\ud83d\udc38\ud83d\udc9a\ud83d\udc7b\ud83d\ude08\ud83d\udc95\u264d\ufe0f\ud83c\udf38\ud83c\udf34\ud83c\udf3a\ud83c\udf4d\ud83c\udf79\u2615\ufe0f\ud83c\udf6b\u2708\ufe0f\ud83d\udc5c\ud83d\udc80\ud83d\udc09\ud83d\udd25"}, "original_text": "8/26 1022AM: Simulated radar from HRRR through this evening. Life-threatening flooding risk in SE TX - including HO\u2026 https://t.co/0jX4EZ23N5", "id2": "901464954989162497", "tweet_types": {"deleted_tweet": 0, "retweet": "901464954989162497", "quote_tweet": 0, "reply": 0, "original_tweet": 0}}, {"id": "901473265562124289", "text": "RT @TxStormChasers: 8/26 1022AM: Simulated radar from HRRR through this evening. Life-threatening flooding risk in SE TX - including HO\u2026 ", "created_at": {"$date": "2017-08-26T15:55:49Z"}, "favorites_count": 0, "user": {"screen_name": "AggieZach10", "name": "AggieZach", "id": "20432756", "friends": 716, "followers": 488, "verified": false, "account_created_at": {"$date": "2009-02-09T12:52:57Z"}, "description": "Fightin Texas Aggie Class of '05. Husband to a beautiful Aggie woman Class of '04 and father to future Fightin Texas Aggies Class of 2028, 2031 & 2038!"}, "original_text": "8/26 1022AM: Simulated radar from HRRR through this evening. Life-threatening flooding risk in SE TX - including HO\u2026 https://t.co/0jX4EZ23N5", "id2": "901464954989162497", "tweet_types": {"deleted_tweet": 0, "retweet": "901464954989162497", "quote_tweet": 0, "reply": 0, "original_tweet": 0}}, {"id": "901473320679428096", "text": "RT @TxStormChasers: 8/26 1022AM: Simulated radar from HRRR through this evening. Life-threatening flooding risk in SE TX - including HO\u2026 ", "created_at": {"$date": "2017-08-26T15:56:02Z"}, "favorites_count": 0, "user": {"screen_name": "jrenea_tx", "name": "Jrenea", "id": "4273761162", "friends": 896, "followers": 616, "verified": false, "account_created_at": {"$date": "2015-11-18T01:56:06Z"}, "location": "Texas, USA", "description": "Honored to have a Firefighter/Paramedic son, USAF son in law, Oil Field worker son. My millennials are hard working kids. #Conservative #Christian \ud83c\uddfa\ud83c\uddf8"}, "original_text": "8/26 1022AM: Simulated radar from HRRR through this evening. Life-threatening flooding risk in SE TX - including HO\u2026 https://t.co/0jX4EZ23N5", "id2": "901464954989162497", "tweet_types": {"deleted_tweet": 0, "retweet": "901464954989162497", "quote_tweet": 0, "reply": 0, "original_tweet": 0}}, {"id": "901530792265961472", "text": "RT @TxStormChasers: 8/26 1022AM: Simulated radar from HRRR through this evening. Life-threatening flooding risk in SE TX - including HO\u2026 ", "created_at": {"$date": "2017-08-26T19:44:25Z"}, "favorites_count": 0, "user": {"screen_name": "KleinPics", "name": "Klein", "id": "3320999547", "friends": 89, "followers": 122, "verified": false, "account_created_at": {"$date": "2015-06-12T14:34:02Z"}, "description": "A lot of pics are nice Creations of The Creator"}, "original_text": "8/26 1022AM: Simulated radar from HRRR through this evening. Life-threatening flooding risk in SE TX - including HO\u2026 https://t.co/0jX4EZ23N5", "id2": "901464954989162497", "tweet_types": {"deleted_tweet": 0, "retweet": "901464954989162497", "quote_tweet": 0, "reply": 0, "original_tweet": 0}}, {"id": "901546728431603712", "text": "RT @TxStormChasers: 8/26 1022AM: Simulated radar from HRRR through this evening. Life-threatening flooding risk in SE TX - including HO\u2026 ", "created_at": {"$date": "2017-08-26T20:47:44Z"}, "favorites_count": 0, "user": {"screen_name": "B1860", "name": "Tyson", "id": "66624545", "friends": 30, "followers": 9, "verified": false, "account_created_at": {"$date": "2009-08-18T07:35:40Z"}, "location": "South Korea", "description": null}, "original_text": "8/26 1022AM: Simulated radar from HRRR through this evening. Life-threatening flooding risk in SE TX - including HO\u2026 https://t.co/0jX4EZ23N5", "id2": "901464954989162497", "tweet_types": {"deleted_tweet": 0, "retweet": "901464954989162497", "quote_tweet": 0, "reply": 0, "original_tweet": 0}}, {"id": "901465035926646784", "text": "RT @TxStormChasers: 8/26 1022AM: Simulated radar from HRRR through this evening. Life-threatening flooding risk in SE TX - including HO\u2026 ", "created_at": {"$date": "2017-08-26T15:23:07Z"}, "favorites_count": 0, "user": {"screen_name": "populationme", "name": "\u26be\ufe0fGabbin", "id": "433102500", "friends": 607, "followers": 132, "verified": false, "account_created_at": {"$date": "2011-12-10T04:29:11Z"}, "location": "Houston, TX", "description": "Living one day at a time. | #HustleTown"}, "original_text": "8/26 1022AM: Simulated radar from HRRR through this evening. Life-threatening flooding risk in SE TX - including HO\u2026 https://t.co/0jX4EZ23N5", "id2": "901464954989162497", "tweet_types": {"deleted_tweet": 0, "retweet": "901464954989162497", "quote_tweet": 0, "reply": 0, "original_tweet": 0}}, {"id": "901465125785223170", "text": "RT @TxStormChasers: 8/26 1022AM: Simulated radar from HRRR through this evening. Life-threatening flooding risk in SE TX - including HO\u2026 ", "created_at": {"$date": "2017-08-26T15:23:29Z"}, "favorites_count": 0, "user": {"screen_name": "jt_louw", "name": "Johannes (JT) Louw", "id": "421934086", "friends": 2042, "followers": 278, "verified": false, "account_created_at": {"$date": "2011-11-26T15:45:45Z"}, "location": "Ulsan, Republic of Korea", "description": "Oakdale Agricultural High School 2004 Studied B.Ed: Intermediate & Senior Phase at UNISA. Worked at The Oxford School, Dubai. Working at Hivel English Academy."}, "original_text": "8/26 1022AM: Simulated radar from HRRR through this evening. Life-threatening flooding risk in SE TX - including HO\u2026 https://t.co/0jX4EZ23N5", "id2": "901464954989162497", "tweet_types": {"deleted_tweet": 0, "retweet": "901464954989162497", "quote_tweet": 0, "reply": 0, "original_tweet": 0}}, {"id": "901465167489368064", "text": "RT @TxStormChasers: 8/26 1022AM: Simulated radar from HRRR through this evening. Life-threatening flooding risk in SE TX - including HO\u2026 ", "created_at": {"$date": "2017-08-26T15:23:38Z"}, "favorites_count": 0, "user": {"screen_name": "lastcrazyhorn", "name": "Val (LCH) \u03df", "id": "225147853", "friends": 664, "followers": 679, "verified": false, "account_created_at": {"$date": "2010-12-10T20:35:46Z"}, "location": "Denton, Texas (hometown in NC)", "description": "Aspie musician (B.M.), artist and writer. #Slytherin. Information hunter-gatherer. Skywarn storm spotter!  I identify as agender."}, "original_text": "8/26 1022AM: Simulated radar from HRRR through this evening. Life-threatening flooding risk in SE TX - including HO\u2026 https://t.co/0jX4EZ23N5", "id2": "901464954989162497", "tweet_types": {"deleted_tweet": 0, "retweet": "901464954989162497", "quote_tweet": 0, "reply": 0, "original_tweet": 0}}, {"id": "901465304932515840", "text": "RT @TxStormChasers: 8/26 1022AM: Simulated radar from HRRR through this evening. Life-threatening flooding risk in SE TX - including HO\u2026 ", "created_at": {"$date": "2017-08-26T15:24:11Z"}, "favorites_count": 0, "user": {"screen_name": "chapyz80", "name": "Norma Saldivar", "id": "735697276987809792", "friends": 236, "followers": 263, "verified": false, "account_created_at": {"$date": "2016-05-26T05:01:14Z"}, "location": "Laredo, TX", "description": "Weather observer, love thunderstorms, lighting, rain.. \u26a1\ufe0f\u270c\ufe0flove taking pictures, I'm not a professional, just a simple person trying to catch the best panoramas"}, "original_text": "8/26 1022AM: Simulated radar from HRRR through this evening. Life-threatening flooding risk in SE TX - including HO\u2026 https://t.co/0jX4EZ23N5", "id2": "901464954989162497", "tweet_types": {"deleted_tweet": 0, "retweet": "901464954989162497", "quote_tweet": 0, "reply": 0, "original_tweet": 0}}, {"id": "901465309185527810", "text": "RT @TxStormChasers: 8/26 1022AM: Simulated radar from HRRR through this evening. Life-threatening flooding risk in SE TX - including HO\u2026 ", "created_at": {"$date": "2017-08-26T15:24:12Z"}, "favorites_count": 0, "user": {"screen_name": "ChouchouTreger", "name": "treguer", "id": "802599134200995840", "friends": 732, "followers": 274, "verified": false, "account_created_at": {"$date": "2016-11-26T19:45:19Z"}, "description": "#NoDAPL\n \n#GoHome We are stronger than you\n#Charlottesville\n #UnitedWithIsrael\n #ObjecteurenConscience \n\n \n\nPr une vraie #JusticeInternationale."}, "original_text": "8/26 1022AM: Simulated radar from HRRR through this evening. Life-threatening flooding risk in SE TX - including HO\u2026 https://t.co/0jX4EZ23N5", "id2": "901464954989162497", "tweet_types": {"deleted_tweet": 0, "retweet": "901464954989162497", "quote_tweet": 0, "reply": 0, "original_tweet": 0}}, {"id": "901465599045513216", "text": "RT @TxStormChasers: 8/26 1022AM: Simulated radar from HRRR through this evening. Life-threatening flooding risk in SE TX - including HO\u2026 ", "created_at": {"$date": "2017-08-26T15:25:21Z"}, "favorites_count": 0, "user": {"screen_name": "kschones84", "name": "KScho", "id": "2426453688", "friends": 138, "followers": 232, "verified": false, "account_created_at": {"$date": "2014-04-04T01:37:30Z"}, "description": null}, "original_text": "8/26 1022AM: Simulated radar from HRRR through this evening. Life-threatening flooding risk in SE TX - including HO\u2026 https://t.co/0jX4EZ23N5", "id2": "901464954989162497", "tweet_types": {"deleted_tweet": 0, "retweet": "901464954989162497", "quote_tweet": 0, "reply": 0, "original_tweet": 0}}, {"id": "901465696273481728", "text": "RT @TxStormChasers: 8/26 1022AM: Simulated radar from HRRR through this evening. Life-threatening flooding risk in SE TX - including HO\u2026 ", "created_at": {"$date": "2017-08-26T15:25:45Z"}, "favorites_count": 0, "user": {"screen_name": "PollyG88", "name": "PollyG", "id": "518828743", "friends": 762, "followers": 311, "verified": false, "account_created_at": {"$date": "2012-03-08T20:08:28Z"}, "description": "Holistic Health Coach @ My Citrus Craving. IIN graduate. Wife. Mother. Health enthusiast. Political Moderate. Music lover."}, "original_text": "8/26 1022AM: Simulated radar from HRRR through this evening. Life-threatening flooding risk in SE TX - including HO\u2026 https://t.co/0jX4EZ23N5", "id2": "901464954989162497", "tweet_types": {"deleted_tweet": 0, "retweet": "901464954989162497", "quote_tweet": 0, "reply": 0, "original_tweet": 0}}, {"id": "901465819376439299", "text": "RT @TxStormChasers: 8/26 1022AM: Simulated radar from HRRR through this evening. Life-threatening flooding risk in SE TX - including HO\u2026 ", "created_at": {"$date": "2017-08-26T15:26:14Z"}, "favorites_count": 0, "user": {"screen_name": "MizzPinkSin", "name": "Alexi", "id": "741661131001892864", "friends": 464, "followers": 168, "verified": false, "account_created_at": {"$date": "2016-06-11T15:59:27Z"}, "location": "Texas, USA", "description": "When life seems to be letting you down, just remember that you're awesome just the way you are. Pick yourself up and dust yourself off and carry on!"}, "original_text": "8/26 1022AM: Simulated radar from HRRR through this evening. Life-threatening flooding risk in SE TX - including HO\u2026 https://t.co/0jX4EZ23N5", "id2": "901464954989162497", "tweet_types": {"deleted_tweet": 0, "retweet": "901464954989162497", "quote_tweet": 0, "reply": 0, "original_tweet": 0}}, {"id": "901465976474152960", "text": "RT @TxStormChasers: 8/26 1022AM: Simulated radar from HRRR through this evening. Life-threatening flooding risk in SE TX - including HO\u2026 ", "created_at": {"$date": "2017-08-26T15:26:51Z"}, "favorites_count": 0, "user": {"screen_name": "TRAVELSnCHASES", "name": "Travels & Chases", "id": "284734321", "friends": 237, "followers": 604, "verified": false, "account_created_at": {"$date": "2011-04-19T21:33:24Z"}, "location": "Queens , New York ", "description": "World Traveler, fascinated w/ severe weather ,tweeting daily about historic tornadoes of the past. Each May I chase & document storms in the Great Plains w/ SLT"}, "original_text": "8/26 1022AM: Simulated radar from HRRR through this evening. Life-threatening flooding risk in SE TX - including HO\u2026 https://t.co/0jX4EZ23N5", "id2": "901464954989162497", "tweet_types": {"deleted_tweet": 0, "retweet": "901464954989162497", "quote_tweet": 0, "reply": 0, "original_tweet": 0}}, {"id": "901466024834420737", "text": "RT @TxStormChasers: 8/26 1022AM: Simulated radar from HRRR through this evening. Life-threatening flooding risk in SE TX - including HO\u2026 ", "created_at": {"$date": "2017-08-26T15:27:03Z"}, "favorites_count": 0, "user": {"screen_name": "WxJoeZamp", "name": "Joe Zampitella", "id": "2573173092", "friends": 392, "followers": 402, "verified": false, "account_created_at": {"$date": "2014-06-17T16:24:57Z"}, "location": "Boston / Oklahoma / America", "description": "big data & business analytics // +TSRA // runnin' just in case"}, "original_text": "8/26 1022AM: Simulated radar from HRRR through this evening. Life-threatening flooding risk in SE TX - including HO\u2026 https://t.co/0jX4EZ23N5", "id2": "901464954989162497", "tweet_types": {"deleted_tweet": 0, "retweet": "901464954989162497", "quote_tweet": 0, "reply": 0, "original_tweet": 0}}, {"id": "901466326669160449", "text": "RT @TxStormChasers: 8/26 1022AM: Simulated radar from HRRR through this evening. Life-threatening flooding risk in SE TX - including HO\u2026 ", "created_at": {"$date": "2017-08-26T15:28:15Z"}, "favorites_count": 0, "user": {"screen_name": "aLoboinTexas", "name": "Charles Gibbons", "id": "971069755", "friends": 104, "followers": 34, "verified": false, "account_created_at": {"$date": "2012-11-26T00:41:13Z"}, "location": "Hurst Texas", "description": "UNM Lobo. Husband. Dad. Engineer. Home brewer. VW aficionado. Likes to think he's kinda smart."}, "original_text": "8/26 1022AM: Simulated radar from HRRR through this evening. Life-threatening flooding risk in SE TX - including HO\u2026 https://t.co/0jX4EZ23N5", "id2": "901464954989162497", "tweet_types": {"deleted_tweet": 0, "retweet": "901464954989162497", "quote_tweet": 0, "reply": 0, "original_tweet": 0}}, {"id": "901536009128747008", "text": "RT @TxStormChasers: 8/26 1022AM: Simulated radar from HRRR through this evening. Life-threatening flooding risk in SE TX - including HO\u2026 ", "created_at": {"$date": "2017-08-26T20:05:08Z"}, "favorites_count": 0, "user": {"screen_name": "texleex", "name": "lex", "id": "1685045946", "friends": 1910, "followers": 884, "verified": false, "account_created_at": {"$date": "2013-08-20T06:53:48Z"}, "location": "obsessed w/hamilton in the agg", "description": "trying to fit the pieces back together"}, "original_text": "8/26 1022AM: Simulated radar from HRRR through this evening. Life-threatening flooding risk in SE TX - including HO\u2026 https://t.co/0jX4EZ23N5", "id2": "901464954989162497", "tweet_types": {"deleted_tweet": 0, "retweet": "901464954989162497", "quote_tweet": 0, "reply": 0, "original_tweet": 0}}]