[{"id": "901562611485089792", "text": "RT @KPRC2WEATHER: Three spots of potential rotation within the tornado warned area. Take cover now if you're in the red box! https://t.co/L\u2026", "created_at": {"$date": "2017-08-26T21:50:51Z"}, "favorites_count": 0, "user": {"screen_name": "_KingT", "name": "DeadShot", "id": "35307123", "friends": 673, "followers": 1008, "verified": false, "account_created_at": {"$date": "2009-04-25T20:51:11Z"}, "location": "Texas", "description": "[ Rest In Paradise @Mr_AcresHome ] [ Glo In Peace @HOVoVONTE ] [ Keep The Legend A Myth\u2122 ] #BornKing"}, "original_text": "Three spots of potential rotation within the tornado warned area. Take cover now if you're in the red box! https://t.co/Lb5932gBPd", "id2": "901562016376254464", "tweet_types": {"deleted_tweet": 0, "retweet": "901562016376254464", "quote_tweet": 0, "reply": 0, "original_tweet": 0}}, {"id": "901563795222515713", "text": "RT @KPRC2WEATHER: Three spots of potential rotation within the tornado warned area. Take cover now if you're in the red box! https://t.co/L\u2026", "created_at": {"$date": "2017-08-26T21:55:33Z"}, "favorites_count": 0, "user": {"screen_name": "ChiNewsBench", "name": "Chicago News Bench\u2122", "id": "20016443", "friends": 5121, "followers": 5761, "verified": false, "account_created_at": {"$date": "2009-02-04T00:22:22Z"}, "location": "Houston, Texas USA", "description": "Battling leftists since 1976. Please help support my lifelong fight to #MAGA: http://paypal.me/homelesspatriot"}, "original_text": "Three spots of potential rotation within the tornado warned area. Take cover now if you're in the red box! https://t.co/Lb5932gBPd", "id2": "901562016376254464", "tweet_types": {"deleted_tweet": 0, "retweet": "901562016376254464", "quote_tweet": 0, "reply": 0, "original_tweet": 0}}, {"id": "901562090007257090", "text": "RT @KPRC2WEATHER: Three spots of potential rotation within the tornado warned area. Take cover now if you're in the red box! https://t.co/L\u2026", "created_at": {"$date": "2017-08-26T21:48:47Z"}, "favorites_count": 0, "user": {"screen_name": "AmazingGreis", "name": "Greis", "id": "15656069", "friends": 1961, "followers": 3540, "verified": false, "account_created_at": {"$date": "2008-07-30T03:44:23Z"}, "location": "Deep in the \u2764\ufe0f Of Texas!", "description": "Pronounced Grace. Always amazing & occasionally under fire! An Astros loving Texan! Will #Swoon for Jake. I was in the paper once: http://tinyurl.com/k2mvduu"}, "original_text": "Three spots of potential rotation within the tornado warned area. Take cover now if you're in the red box! https://t.co/Lb5932gBPd", "id2": "901562016376254464", "tweet_types": {"deleted_tweet": 0, "retweet": "901562016376254464", "quote_tweet": 0, "reply": 0, "original_tweet": 0}}, {"id": "901562257334837248", "text": "RT @KPRC2WEATHER: Three spots of potential rotation within the tornado warned area. Take cover now if you're in the red box! https://t.co/L\u2026", "created_at": {"$date": "2017-08-26T21:49:27Z"}, "favorites_count": 0, "user": {"screen_name": "clintyoung91", "name": "Clint Young", "id": "181361050", "friends": 32, "followers": 54, "verified": false, "account_created_at": {"$date": "2010-08-22T00:41:40Z"}, "location": "Houston", "description": null}, "original_text": "Three spots of potential rotation within the tornado warned area. Take cover now if you're in the red box! https://t.co/Lb5932gBPd", "id2": "901562016376254464", "tweet_types": {"deleted_tweet": 0, "retweet": "901562016376254464", "quote_tweet": 0, "reply": 0, "original_tweet": 0}}, {"id": "901562377157718017", "text": "RT @KPRC2WEATHER: Three spots of potential rotation within the tornado warned area. Take cover now if you're in the red box! https://t.co/L\u2026", "created_at": {"$date": "2017-08-26T21:49:55Z"}, "favorites_count": 0, "user": {"screen_name": "saulleal86", "name": "Saul Leal", "id": "724329070524129280", "friends": 1193, "followers": 137, "verified": false, "account_created_at": {"$date": "2016-04-24T20:08:02Z"}, "location": "Houston, TX.             Tamps", "description": "\u26bdclub Am\u00e9rica\n\u26bdreal Madrid\n\ud83c\udfc8Dallas Cowboys\n\ud83c\udfc0San Antonio Spurs\n\u26be Texas Rangers"}, "original_text": "Three spots of potential rotation within the tornado warned area. Take cover now if you're in the red box! https://t.co/Lb5932gBPd", "id2": "901562016376254464", "tweet_types": {"deleted_tweet": 0, "retweet": "901562016376254464", "quote_tweet": 0, "reply": 0, "original_tweet": 0}}, {"id": "901562238108147712", "text": "RT @KPRC2WEATHER: Three spots of potential rotation within the tornado warned area. Take cover now if you're in the red box! https://t.co/L\u2026", "created_at": {"$date": "2017-08-26T21:49:22Z"}, "favorites_count": 0, "user": {"screen_name": "TheReal_Madz", "name": "The Madisen Williams", "id": "3012555516", "friends": 680, "followers": 790, "verified": false, "account_created_at": {"$date": "2015-02-07T17:23:43Z"}, "location": "Baytown, Tx \ud83c\udf0a", "description": "21 | @Breewainscott | #CowboysNation | #DukeBasketball |"}, "original_text": "Three spots of potential rotation within the tornado warned area. Take cover now if you're in the red box! https://t.co/Lb5932gBPd", "id2": "901562016376254464", "tweet_types": {"deleted_tweet": 0, "retweet": "901562016376254464", "quote_tweet": 0, "reply": 0, "original_tweet": 0}}, {"id": "901562253832540160", "text": "RT @KPRC2WEATHER: Three spots of potential rotation within the tornado warned area. Take cover now if you're in the red box! https://t.co/L\u2026", "created_at": {"$date": "2017-08-26T21:49:26Z"}, "favorites_count": 0, "user": {"screen_name": "ttlle", "name": "ttlle", "id": "63074585", "friends": 417, "followers": 524, "verified": false, "account_created_at": {"$date": "2009-08-05T08:30:15Z"}, "location": "Houston", "description": null}, "original_text": "Three spots of potential rotation within the tornado warned area. Take cover now if you're in the red box! https://t.co/Lb5932gBPd", "id2": "901562016376254464", "tweet_types": {"deleted_tweet": 0, "retweet": "901562016376254464", "quote_tweet": 0, "reply": 0, "original_tweet": 0}}]