[{"id": "903647341244293121", "text": "@fbcoem https://t.co/siKKTL4f24", "created_at": {"$date": "2017-09-01T15:54:49Z"}, "favorites_count": 0, "user": {"screen_name": "NathanF56595065", "name": "Nathan Fraser", "id": "903647102307368961", "friends": 0, "followers": 0, "verified": false, "account_created_at": {"$date": "2017-09-01T15:53:52Z"}, "description": null}, "id2": "903634970207539200", "tweet_types": {"deleted_tweet": 0, "retweet": 0, "quote_tweet": 0, "reply": "903634970207539200", "original_tweet": 0}}, {"id": "903668570529427456", "text": "@fbcoem Finally, it should be all downhill from here, literally! #RoadtoRecovery #Harvey #SugarLand", "created_at": {"$date": "2017-09-01T17:19:11Z"}, "favorites_count": 0, "user": {"screen_name": "james_arrow", "name": "James Arrow", "id": "453373056", "friends": 1827, "followers": 628, "verified": false, "account_created_at": {"$date": "2012-01-02T21:22:47Z"}, "location": "Houston, TX", "description": "Proud father and husband | lover of good company, great music, fine food & wine | capital projects SME & risk manager by day @BoozAllen.\nOpinions are my own \ud83d\udcad"}, "id2": "903634970207539200", "tweet_types": {"deleted_tweet": 0, "retweet": 0, "quote_tweet": 0, "reply": "903634970207539200", "original_tweet": 0}}, {"id": "903635236084469761", "text": "@fbcoem Hallelujah!", "created_at": {"$date": "2017-09-01T15:06:43Z"}, "favorites_count": 0, "user": {"screen_name": "SherryCISM", "name": "Sherry Cardinal", "id": "768929895351103488", "friends": 26, "followers": 16, "verified": false, "account_created_at": {"$date": "2016-08-25T21:55:47Z"}, "location": "Fort Bend County, Texas", "description": "Sherry's the name, critical incident stress management is my game!"}, "geolocation": "Sugar Land, TX", "id2": "903634970207539200", "tweet_types": {"deleted_tweet": 0, "retweet": 0, "quote_tweet": 0, "reply": "903634970207539200", "original_tweet": 0}}, {"id": "903639689101545473", "text": "@fbcoem Thank you for the updates.  When will the evacuation orders be lifted?", "created_at": {"$date": "2017-09-01T15:24:25Z"}, "favorites_count": 0, "user": {"screen_name": "Russell94627540", "name": "Russell Collins", "id": "846062495756374018", "friends": 50, "followers": 10, "verified": false, "account_created_at": {"$date": "2017-03-26T18:13:12Z"}, "description": null}, "id2": "903634970207539200", "tweet_types": {"deleted_tweet": 0, "retweet": 0, "quote_tweet": 0, "reply": "903634970207539200", "original_tweet": 0}}, {"id": "903643759577051136", "text": "RT @fbcoem: Update from NWS- at 9:15AM https://t.co/kCMZi0bxEY", "created_at": {"$date": "2017-09-01T15:40:35Z"}, "favorites_count": 0, "user": {"screen_name": "edmugonza", "name": "Eduardo Munoz", "id": "94603917", "friends": 491, "followers": 61, "verified": false, "account_created_at": {"$date": "2009-12-04T17:43:08Z"}, "description": null}, "original_text": "Update from NWS- at 9:15AM https://t.co/kCMZi0bxEY", "id2": "903634970207539200", "tweet_types": {"deleted_tweet": 0, "retweet": "903634970207539200", "quote_tweet": 0, "reply": 0, "original_tweet": 0}}, {"id": "903643936182468609", "text": "RT @fbcoem: Update from NWS- at 9:15AM https://t.co/kCMZi0bxEY", "created_at": {"$date": "2017-09-01T15:41:17Z"}, "favorites_count": 0, "user": {"screen_name": "Pb65Jr", "name": "Pat Butler", "id": "2604330670", "friends": 1139, "followers": 321, "verified": false, "account_created_at": {"$date": "2014-06-12T18:06:43Z"}, "location": "USA ", "description": "dad, Kentuckian, vet, likes pizza; reTweets may imply agreement"}, "original_text": "Update from NWS- at 9:15AM https://t.co/kCMZi0bxEY", "id2": "903634970207539200", "tweet_types": {"deleted_tweet": 0, "retweet": "903634970207539200", "quote_tweet": 0, "reply": 0, "original_tweet": 0}}, {"id": "903644194740326401", "text": "RT @fbcoem: Update from NWS- at 9:15AM https://t.co/kCMZi0bxEY", "created_at": {"$date": "2017-09-01T15:42:19Z"}, "favorites_count": 0, "user": {"screen_name": "faziarizvi", "name": "Fazia Begum Rizvi", "id": "10136872", "friends": 1278, "followers": 1401, "verified": false, "account_created_at": {"$date": "2007-11-10T21:39:59Z"}, "location": "Texas", "description": "Writer. Actor. Anthropologist. Geek."}, "original_text": "Update from NWS- at 9:15AM https://t.co/kCMZi0bxEY", "id2": "903634970207539200", "tweet_types": {"deleted_tweet": 0, "retweet": "903634970207539200", "quote_tweet": 0, "reply": 0, "original_tweet": 0}}, {"id": "903644554179608578", "text": "RT @fbcoem: Update from NWS- at 9:15AM https://t.co/kCMZi0bxEY", "created_at": {"$date": "2017-09-01T15:43:45Z"}, "favorites_count": 0, "user": {"screen_name": "AllHazardsTFS", "name": "TXA&M Forest Service", "id": "3309103381", "friends": 228, "followers": 3779, "verified": true, "account_created_at": {"$date": "2015-08-07T20:48:28Z"}, "location": "College Station, TX", "description": "In addition to fighting wildfires, TFS is called upon to assist during all-hazard emergencies such as natural and man-made disasters and domestic situations."}, "original_text": "Update from NWS- at 9:15AM https://t.co/kCMZi0bxEY", "id2": "903634970207539200", "tweet_types": {"deleted_tweet": 0, "retweet": "903634970207539200", "quote_tweet": 0, "reply": 0, "original_tweet": 0}}, {"id": "903644551834984448", "text": "RT @fbcoem: Update from NWS- at 9:15AM https://t.co/kCMZi0bxEY", "created_at": {"$date": "2017-09-01T15:43:44Z"}, "favorites_count": 0, "user": {"screen_name": "KHS_GirlsHoops", "name": "Kempner Girls Bball", "id": "3698539050", "friends": 240, "followers": 182, "verified": false, "account_created_at": {"$date": "2015-09-27T01:42:39Z"}, "location": "Sugar Land, TX", "description": "We Over me"}, "original_text": "Update from NWS- at 9:15AM https://t.co/kCMZi0bxEY", "id2": "903634970207539200", "tweet_types": {"deleted_tweet": 0, "retweet": "903634970207539200", "quote_tweet": 0, "reply": 0, "original_tweet": 0}}, {"id": "903644837378961409", "text": "RT @fbcoem: Update from NWS- at 9:15AM https://t.co/kCMZi0bxEY", "created_at": {"$date": "2017-09-01T15:44:52Z"}, "favorites_count": 0, "user": {"screen_name": "iron_rations", "name": "IRON RATIONS", "id": "2959974260", "friends": 1409, "followers": 452, "verified": false, "account_created_at": {"$date": "2015-01-05T18:41:01Z"}, "description": null}, "original_text": "Update from NWS- at 9:15AM https://t.co/kCMZi0bxEY", "id2": "903634970207539200", "tweet_types": {"deleted_tweet": 0, "retweet": "903634970207539200", "quote_tweet": 0, "reply": 0, "original_tweet": 0}}, {"id": "903645611286777856", "text": "RT @fbcoem: Update from NWS- at 9:15AM https://t.co/kCMZi0bxEY", "created_at": {"$date": "2017-09-01T15:47:57Z"}, "favorites_count": 0, "user": {"screen_name": "james_arrow", "name": "James Arrow", "id": "453373056", "friends": 1827, "followers": 628, "verified": false, "account_created_at": {"$date": "2012-01-02T21:22:47Z"}, "location": "Houston, TX", "description": "Proud father and husband | lover of good company, great music, fine food & wine | capital projects SME & risk manager by day @BoozAllen.\nOpinions are my own \ud83d\udcad"}, "original_text": "Update from NWS- at 9:15AM https://t.co/kCMZi0bxEY", "id2": "903634970207539200", "tweet_types": {"deleted_tweet": 0, "retweet": "903634970207539200", "quote_tweet": 0, "reply": 0, "original_tweet": 0}}, {"id": "903645713422311425", "text": "RT @fbcoem: Update from NWS- at 9:15AM https://t.co/kCMZi0bxEY", "created_at": {"$date": "2017-09-01T15:48:21Z"}, "favorites_count": 0, "user": {"screen_name": "svetlanal77", "name": "Svetlana Lazarevic", "id": "725399290974097409", "friends": 38, "followers": 21, "verified": false, "account_created_at": {"$date": "2016-04-27T19:00:43Z"}, "location": "Richmond, TX", "description": null}, "original_text": "Update from NWS- at 9:15AM https://t.co/kCMZi0bxEY", "id2": "903634970207539200", "tweet_types": {"deleted_tweet": 0, "retweet": "903634970207539200", "quote_tweet": 0, "reply": 0, "original_tweet": 0}}, {"id": "903645851712720900", "text": "RT @fbcoem: Update from NWS- at 9:15AM https://t.co/kCMZi0bxEY", "created_at": {"$date": "2017-09-01T15:48:54Z"}, "favorites_count": 0, "user": {"screen_name": "sbperla", "name": "Shiela Perla", "id": "258861607", "friends": 118, "followers": 46, "verified": false, "account_created_at": {"$date": "2011-02-28T17:23:24Z"}, "location": "Texas, USA", "description": null}, "original_text": "Update from NWS- at 9:15AM https://t.co/kCMZi0bxEY", "id2": "903634970207539200", "tweet_types": {"deleted_tweet": 0, "retweet": "903634970207539200", "quote_tweet": 0, "reply": 0, "original_tweet": 0}}, {"id": "903646020751503360", "text": "RT @fbcoem: Update from NWS- at 9:15AM https://t.co/kCMZi0bxEY", "created_at": {"$date": "2017-09-01T15:49:34Z"}, "favorites_count": 0, "user": {"screen_name": "TibbsFam", "name": "Tibbs Fam", "id": "2584218650", "friends": 934, "followers": 432, "verified": false, "account_created_at": {"$date": "2014-06-23T15:56:36Z"}, "location": "Hoover, AL", "description": "Football family. Furman Paladins/Alabama Crimson Tide Following Jesus. Weather watchers. (Tweets mostly by the Mrs.)"}, "original_text": "Update from NWS- at 9:15AM https://t.co/kCMZi0bxEY", "id2": "903634970207539200", "tweet_types": {"deleted_tweet": 0, "retweet": "903634970207539200", "quote_tweet": 0, "reply": 0, "original_tweet": 0}}, {"id": "903646304739446784", "text": "RT @fbcoem: Update from NWS- at 9:15AM https://t.co/kCMZi0bxEY", "created_at": {"$date": "2017-09-01T15:50:42Z"}, "favorites_count": 0, "user": {"screen_name": "abosife2010", "name": "abdulrahman abosife", "id": "319801657", "friends": 2929, "followers": 847, "verified": false, "account_created_at": {"$date": "2011-06-18T19:27:41Z"}, "location": "\u0639\u0628\u062f\u0627\u0644\u0631\u062d\u0645\u0646 \u0627\u0628\u0648\u0633\u064a\u0641", "description": "SIFEBOOK"}, "original_text": "Update from NWS- at 9:15AM https://t.co/kCMZi0bxEY", "id2": "903634970207539200", "tweet_types": {"deleted_tweet": 0, "retweet": "903634970207539200", "quote_tweet": 0, "reply": 0, "original_tweet": 0}}, {"id": "903646733162487808", "text": "RT @fbcoem: Update from NWS- at 9:15AM https://t.co/kCMZi0bxEY", "created_at": {"$date": "2017-09-01T15:52:24Z"}, "favorites_count": 0, "user": {"screen_name": "GlutenQueen", "name": "ThousandAire", "id": "232106713", "friends": 1898, "followers": 1662, "verified": false, "account_created_at": {"$date": "2010-12-30T07:38:06Z"}, "location": "Land of Sugar * Republic of TX", "description": "Gluten Free ~ Pool Player ~ Music Lover ~ Animal Lover ~ Pescetarian ~ Karaoke Queen ~ Southpaw ~ Czexan!  \u2708 & photography are my raison d'etre! \ud83c\uddfa\ud83c\uddf8\ud83c\udde8\ud83c\uddff"}, "original_text": "Update from NWS- at 9:15AM https://t.co/kCMZi0bxEY", "id2": "903634970207539200", "tweet_types": {"deleted_tweet": 0, "retweet": "903634970207539200", "quote_tweet": 0, "reply": 0, "original_tweet": 0}}, {"id": "903647053833797632", "text": "RT @fbcoem: Update from NWS- at 9:15AM https://t.co/kCMZi0bxEY", "created_at": {"$date": "2017-09-01T15:53:41Z"}, "favorites_count": 0, "user": {"screen_name": "pamelamadngdong", "name": "Pamela T.", "id": "987949386", "friends": 221, "followers": 88, "verified": false, "account_created_at": {"$date": "2012-12-04T03:41:13Z"}, "location": "Houston, Texas", "description": "Devoted Mommy and Trophy Wife, NPC Novice Bikini Competitor"}, "original_text": "Update from NWS- at 9:15AM https://t.co/kCMZi0bxEY", "id2": "903634970207539200", "tweet_types": {"deleted_tweet": 0, "retweet": "903634970207539200", "quote_tweet": 0, "reply": 0, "original_tweet": 0}}, {"id": "903647994867851265", "text": "RT @fbcoem: Update from NWS- at 9:15AM https://t.co/kCMZi0bxEY", "created_at": {"$date": "2017-09-01T15:57:25Z"}, "favorites_count": 0, "user": {"screen_name": "Theactualhashmi", "name": "Wasiq Hashmi", "id": "69772747", "friends": 375, "followers": 813, "verified": false, "account_created_at": {"$date": "2009-08-29T03:10:28Z"}, "location": "Houston, TX", "description": null}, "original_text": "Update from NWS- at 9:15AM https://t.co/kCMZi0bxEY", "id2": "903634970207539200", "tweet_types": {"deleted_tweet": 0, "retweet": "903634970207539200", "quote_tweet": 0, "reply": 0, "original_tweet": 0}}, {"id": "903651366740078593", "text": "RT @fbcoem: Update from NWS- at 9:15AM https://t.co/kCMZi0bxEY", "created_at": {"$date": "2017-09-01T16:10:49Z"}, "favorites_count": 0, "user": {"screen_name": "MartaFaithLeap", "name": "Marta Alves", "id": "492360357", "friends": 32, "followers": 4, "verified": false, "account_created_at": {"$date": "2012-02-14T16:43:12Z"}, "description": "Webmaster of Leap of Faith"}, "original_text": "Update from NWS- at 9:15AM https://t.co/kCMZi0bxEY", "id2": "903634970207539200", "tweet_types": {"deleted_tweet": 0, "retweet": "903634970207539200", "quote_tweet": 0, "reply": 0, "original_tweet": 0}}, {"id": "903651661096341505", "text": "RT @fbcoem: Update from NWS- at 9:15AM https://t.co/kCMZi0bxEY", "created_at": {"$date": "2017-09-01T16:11:59Z"}, "favorites_count": 0, "user": {"screen_name": "lovenpanes", "name": "Loven Panes", "id": "279699063", "friends": 29, "followers": 13, "verified": false, "account_created_at": {"$date": "2011-04-09T20:41:35Z"}, "description": null}, "original_text": "Update from NWS- at 9:15AM https://t.co/kCMZi0bxEY", "id2": "903634970207539200", "tweet_types": {"deleted_tweet": 0, "retweet": "903634970207539200", "quote_tweet": 0, "reply": 0, "original_tweet": 0}}, {"id": "903651627143397377", "text": "RT @fbcoem: Update from NWS- at 9:15AM https://t.co/kCMZi0bxEY", "created_at": {"$date": "2017-09-01T16:11:51Z"}, "favorites_count": 0, "user": {"screen_name": "RichFM39517086", "name": "WDON RADIO", "id": "1529421373", "friends": 5001, "followers": 2510, "verified": false, "account_created_at": {"$date": "2013-06-19T01:58:01Z"}, "location": "Laguna Beach, Ca", "description": "WDON RADIO ~ # ROCK # BLUES # POP $ LEGENDARY MONEY!!"}, "original_text": "Update from NWS- at 9:15AM https://t.co/kCMZi0bxEY", "id2": "903634970207539200", "tweet_types": {"deleted_tweet": 0, "retweet": "903634970207539200", "quote_tweet": 0, "reply": 0, "original_tweet": 0}}, {"id": "903651644046495744", "text": "RT @fbcoem: Update from NWS- at 9:15AM https://t.co/kCMZi0bxEY", "created_at": {"$date": "2017-09-01T16:11:55Z"}, "favorites_count": 0, "user": {"screen_name": "Travis_Kaeser", "name": "Travis Kaeser", "id": "344479379", "friends": 211, "followers": 463, "verified": false, "account_created_at": {"$date": "2011-07-29T03:42:52Z"}, "description": "UH19"}, "original_text": "Update from NWS- at 9:15AM https://t.co/kCMZi0bxEY", "id2": "903634970207539200", "tweet_types": {"deleted_tweet": 0, "retweet": "903634970207539200", "quote_tweet": 0, "reply": 0, "original_tweet": 0}}, {"id": "903651743959064576", "text": "RT @fbcoem: Update from NWS- at 9:15AM https://t.co/kCMZi0bxEY", "created_at": {"$date": "2017-09-01T16:12:19Z"}, "favorites_count": 0, "user": {"screen_name": "evatrevino1225", "name": "Eva Torres Trevi\u00f1o", "id": "3608835134", "friends": 77, "followers": 23, "verified": false, "account_created_at": {"$date": "2015-09-18T20:57:23Z"}, "location": "Texas, USA", "description": null}, "original_text": "Update from NWS- at 9:15AM https://t.co/kCMZi0bxEY", "id2": "903634970207539200", "tweet_types": {"deleted_tweet": 0, "retweet": "903634970207539200", "quote_tweet": 0, "reply": 0, "original_tweet": 0}}, {"id": "903652270394527746", "text": "RT @fbcoem: Update from NWS- at 9:15AM https://t.co/kCMZi0bxEY", "created_at": {"$date": "2017-09-01T16:14:24Z"}, "favorites_count": 0, "user": {"screen_name": "BMitchRX", "name": "#FuriousStyles", "id": "259043500", "friends": 330, "followers": 154, "verified": false, "account_created_at": {"$date": "2011-03-01T01:27:24Z"}, "location": "Houston, TX ", "description": "God's Kingdom Agenda: the VISIBLE demonstration of God's comprehensive rule over EVERY area of life. Whose agenda are you following?"}, "original_text": "Update from NWS- at 9:15AM https://t.co/kCMZi0bxEY", "id2": "903634970207539200", "tweet_types": {"deleted_tweet": 0, "retweet": "903634970207539200", "quote_tweet": 0, "reply": 0, "original_tweet": 0}}, {"id": "903685393316552705", "text": "RT @fbcoem: Update from NWS- at 9:15AM https://t.co/kCMZi0bxEY", "created_at": {"$date": "2017-09-01T18:26:02Z"}, "favorites_count": 0, "user": {"screen_name": "MADE101org", "name": "M.A.D.E", "id": "474035038", "friends": 30, "followers": 13, "verified": false, "account_created_at": {"$date": "2012-01-25T15:51:34Z"}, "description": "Our goals are geared toward Aspiring through Inspiring our community, youth and adults through outreach events and activities."}, "original_text": "Update from NWS- at 9:15AM https://t.co/kCMZi0bxEY", "id2": "903634970207539200", "tweet_types": {"deleted_tweet": 0, "retweet": "903634970207539200", "quote_tweet": 0, "reply": 0, "original_tweet": 0}}, {"id": "903641544388947968", "text": "RT @fbcoem: Update from NWS- at 9:15AM https://t.co/kCMZi0bxEY", "created_at": {"$date": "2017-09-01T15:31:47Z"}, "favorites_count": 0, "user": {"screen_name": "CaitilinPIO", "name": "Caitilin Espinosa", "id": "44539484", "friends": 2634, "followers": 9396, "verified": false, "account_created_at": {"$date": "2009-06-04T03:52:14Z"}, "location": "Fort Bend County", "description": "#PublicInformationOfficer @FBCSO #socialmedia #communications       Former #TVMeteorologist @Baylor Grad #married #mommy #photoshoots #dogmom"}, "original_text": "Update from NWS- at 9:15AM https://t.co/kCMZi0bxEY", "id2": "903634970207539200", "tweet_types": {"deleted_tweet": 0, "retweet": "903634970207539200", "quote_tweet": 0, "reply": 0, "original_tweet": 0}}, {"id": "903642208154394624", "text": "RT @fbcoem: Update from NWS- at 9:15AM https://t.co/kCMZi0bxEY", "created_at": {"$date": "2017-09-01T15:34:25Z"}, "favorites_count": 0, "user": {"screen_name": "jachildress", "name": "John Childress", "id": "38679440", "friends": 981, "followers": 151, "verified": false, "account_created_at": {"$date": "2009-05-08T14:53:26Z"}, "location": "Sugar Land, TX", "description": null}, "original_text": "Update from NWS- at 9:15AM https://t.co/kCMZi0bxEY", "id2": "903634970207539200", "tweet_types": {"deleted_tweet": 0, "retweet": "903634970207539200", "quote_tweet": 0, "reply": 0, "original_tweet": 0}}, {"id": "903642824381485056", "text": "RT @fbcoem: Update from NWS- at 9:15AM https://t.co/kCMZi0bxEY", "created_at": {"$date": "2017-09-01T15:36:52Z"}, "favorites_count": 0, "user": {"screen_name": "TrueHoustonian", "name": "\u270cNoel\u270c", "id": "350506292", "friends": 431, "followers": 94, "verified": false, "account_created_at": {"$date": "2011-08-07T21:59:52Z"}, "description": null}, "original_text": "Update from NWS- at 9:15AM https://t.co/kCMZi0bxEY", "id2": "903634970207539200", "tweet_types": {"deleted_tweet": 0, "retweet": "903634970207539200", "quote_tweet": 0, "reply": 0, "original_tweet": 0}}, {"id": "903642622065037312", "text": "RT @fbcoem: Update from NWS- at 9:15AM https://t.co/kCMZi0bxEY", "created_at": {"$date": "2017-09-01T15:36:04Z"}, "favorites_count": 0, "user": {"screen_name": "abc13houston", "name": "ABC13 Houston", "id": "16247383", "friends": 1256, "followers": 648513, "verified": true, "account_created_at": {"$date": "2008-09-11T20:45:55Z"}, "location": "Houston, TX", "description": "ABC13 is Houston's news leader. Your number one source for breaking news 24 hours a day/7 days a week."}, "original_text": "Update from NWS- at 9:15AM https://t.co/kCMZi0bxEY", "id2": "903634970207539200", "tweet_types": {"deleted_tweet": 0, "retweet": "903634970207539200", "quote_tweet": 0, "reply": 0, "original_tweet": 0}}, {"id": "903662410854268928", "text": "RT @fbcoem: Update from NWS- at 9:15AM https://t.co/kCMZi0bxEY", "created_at": {"$date": "2017-09-01T16:54:42Z"}, "favorites_count": 0, "user": {"screen_name": "pdiane713", "name": "Peggy", "id": "155774203", "friends": 104, "followers": 20, "verified": false, "account_created_at": {"$date": "2010-06-15T01:55:59Z"}, "location": "Texas, USA", "description": null}, "original_text": "Update from NWS- at 9:15AM https://t.co/kCMZi0bxEY", "id2": "903634970207539200", "tweet_types": {"deleted_tweet": 0, "retweet": "903634970207539200", "quote_tweet": 0, "reply": 0, "original_tweet": 0}}, {"id": "903667301731487745", "text": "RT @fbcoem: Update from NWS- at 9:15AM https://t.co/kCMZi0bxEY", "created_at": {"$date": "2017-09-01T17:14:08Z"}, "favorites_count": 0, "user": {"screen_name": "tbear326", "name": "Brian", "id": "286739529", "friends": 198, "followers": 58, "verified": false, "account_created_at": {"$date": "2011-04-23T16:08:00Z"}, "location": "Katy", "description": "Just a geek who likes a lot of games, books, movies and technology."}, "original_text": "Update from NWS- at 9:15AM https://t.co/kCMZi0bxEY", "id2": "903634970207539200", "tweet_types": {"deleted_tweet": 0, "retweet": "903634970207539200", "quote_tweet": 0, "reply": 0, "original_tweet": 0}}, {"id": "903649543031545860", "text": "RT @fbcoem: Update from NWS- at 9:15AM https://t.co/kCMZi0bxEY", "created_at": {"$date": "2017-09-01T16:03:34Z"}, "favorites_count": 0, "user": {"screen_name": "Line_XIII", "name": "Alex Lin", "id": "3316270657", "friends": 582, "followers": 346, "verified": false, "account_created_at": {"$date": "2015-08-15T20:02:14Z"}, "description": "Diverse tastes of many things that are not super popular mainstream and not top-tier."}, "original_text": "Update from NWS- at 9:15AM https://t.co/kCMZi0bxEY", "id2": "903634970207539200", "tweet_types": {"deleted_tweet": 0, "retweet": "903634970207539200", "quote_tweet": 0, "reply": 0, "original_tweet": 0}}, {"id": "903650340997824514", "text": "RT @fbcoem: Update from NWS- at 9:15AM https://t.co/kCMZi0bxEY", "created_at": {"$date": "2017-09-01T16:06:44Z"}, "favorites_count": 0, "user": {"screen_name": "joshuatcarley", "name": "Joshua T Carley", "id": "888323991504551936", "friends": 5000, "followers": 344, "verified": false, "account_created_at": {"$date": "2017-07-21T09:05:18Z"}, "location": "Houston, TX", "description": null}, "original_text": "Update from NWS- at 9:15AM https://t.co/kCMZi0bxEY", "id2": "903634970207539200", "tweet_types": {"deleted_tweet": 0, "retweet": "903634970207539200", "quote_tweet": 0, "reply": 0, "original_tweet": 0}}, {"id": "903650413391597569", "text": "RT @fbcoem: Update from NWS- at 9:15AM https://t.co/kCMZi0bxEY", "created_at": {"$date": "2017-09-01T16:07:02Z"}, "favorites_count": 0, "user": {"screen_name": "CatDad776", "name": "CatDad776", "id": "18948521", "friends": 1986, "followers": 316, "verified": false, "account_created_at": {"$date": "2009-01-13T19:04:05Z"}, "location": "Texas, USA", "description": "Don't Hate, Celebrate Life"}, "original_text": "Update from NWS- at 9:15AM https://t.co/kCMZi0bxEY", "id2": "903634970207539200", "tweet_types": {"deleted_tweet": 0, "retweet": "903634970207539200", "quote_tweet": 0, "reply": 0, "original_tweet": 0}}, {"id": "903650796658728960", "text": "RT @fbcoem: Update from NWS- at 9:15AM https://t.co/kCMZi0bxEY", "created_at": {"$date": "2017-09-01T16:08:33Z"}, "favorites_count": 0, "user": {"screen_name": "Dannyc121", "name": "Danny Christiansen", "id": "181830942", "friends": 323, "followers": 616, "verified": false, "account_created_at": {"$date": "2010-08-23T04:29:25Z"}, "location": "HTX || SMTX", "description": "Texas State University"}, "original_text": "Update from NWS- at 9:15AM https://t.co/kCMZi0bxEY", "id2": "903634970207539200", "tweet_types": {"deleted_tweet": 0, "retweet": "903634970207539200", "quote_tweet": 0, "reply": 0, "original_tweet": 0}}, {"id": "903691482690756608", "text": "RT @fbcoem: Update from NWS- at 9:15AM https://t.co/kCMZi0bxEY", "created_at": {"$date": "2017-09-01T18:50:13Z"}, "favorites_count": 0, "user": {"screen_name": "marlomolinaro", "name": "Marlo Molinaro", "id": "718526906203656192", "friends": 123, "followers": 107, "verified": false, "account_created_at": {"$date": "2016-04-08T19:52:18Z"}, "description": null}, "original_text": "Update from NWS- at 9:15AM https://t.co/kCMZi0bxEY", "id2": "903634970207539200", "tweet_types": {"deleted_tweet": 0, "retweet": "903634970207539200", "quote_tweet": 0, "reply": 0, "original_tweet": 0}}, {"id": "903658303653376001", "text": "RT @fbcoem: Update from NWS- at 9:15AM https://t.co/kCMZi0bxEY", "created_at": {"$date": "2017-09-01T16:38:23Z"}, "favorites_count": 0, "user": {"screen_name": "chrisab41", "name": "Chris A Brown", "id": "740210206097821697", "friends": 104, "followers": 83, "verified": false, "account_created_at": {"$date": "2016-06-07T15:54:00Z"}, "location": "Texas, USA", "description": null}, "original_text": "Update from NWS- at 9:15AM https://t.co/kCMZi0bxEY", "id2": "903634970207539200", "tweet_types": {"deleted_tweet": 0, "retweet": "903634970207539200", "quote_tweet": 0, "reply": 0, "original_tweet": 0}}, {"id": "903664509692325888", "text": "RT @fbcoem: Update from NWS- at 9:15AM https://t.co/kCMZi0bxEY", "created_at": {"$date": "2017-09-01T17:03:03Z"}, "favorites_count": 0, "user": {"screen_name": "docrocktex26", "name": "Propane Jane\u2122", "id": "16582131", "friends": 4625, "followers": 81615, "verified": false, "account_created_at": {"$date": "2008-10-03T19:08:21Z"}, "location": "Houston, TX", "description": "Wife. Mother. Daughter. Sister. Friend. Doctor. Christian. Longhorn. Liberal. Democrat. Activist. Scorpio. Recycler. Politics Junkie. Proverbial Firestarter."}, "original_text": "Update from NWS- at 9:15AM https://t.co/kCMZi0bxEY", "id2": "903634970207539200", "tweet_types": {"deleted_tweet": 0, "retweet": "903634970207539200", "quote_tweet": 0, "reply": 0, "original_tweet": 0}}, {"id": "903665839781576704", "text": "RT @fbcoem: Update from NWS- at 9:15AM https://t.co/kCMZi0bxEY", "created_at": {"$date": "2017-09-01T17:08:20Z"}, "favorites_count": 0, "user": {"screen_name": "BinderFaith1", "name": "Faith Binder", "id": "788915123012395008", "friends": 580, "followers": 246, "verified": false, "account_created_at": {"$date": "2016-10-20T01:29:57Z"}, "location": "United States", "description": "I read.  I want freedom for all of us . The president is a liar.  Don't follow me; it will make a circle."}, "original_text": "Update from NWS- at 9:15AM https://t.co/kCMZi0bxEY", "id2": "903634970207539200", "tweet_types": {"deleted_tweet": 0, "retweet": "903634970207539200", "quote_tweet": 0, "reply": 0, "original_tweet": 0}}, {"id": "903674894801444864", "text": "RT @fbcoem: Update from NWS- at 9:15AM https://t.co/kCMZi0bxEY", "created_at": {"$date": "2017-09-01T17:44:19Z"}, "favorites_count": 0, "user": {"screen_name": "CnBsNana", "name": "Crystal English", "id": "29967129", "friends": 3258, "followers": 2036, "verified": false, "account_created_at": {"$date": "2009-04-09T11:45:34Z"}, "location": "Pismo Beach, CA", "description": "I Am The Storm"}, "original_text": "Update from NWS- at 9:15AM https://t.co/kCMZi0bxEY", "id2": "903634970207539200", "tweet_types": {"deleted_tweet": 0, "retweet": "903634970207539200", "quote_tweet": 0, "reply": 0, "original_tweet": 0}}, {"id": "903675000821047298", "text": "RT @fbcoem: Update from NWS- at 9:15AM https://t.co/kCMZi0bxEY", "created_at": {"$date": "2017-09-01T17:44:44Z"}, "favorites_count": 0, "user": {"screen_name": "ReedSandee", "name": "Sandee Reed", "id": "743776429", "friends": 75, "followers": 61, "verified": false, "account_created_at": {"$date": "2012-08-07T21:26:33Z"}, "description": "ozark hills artist"}, "original_text": "Update from NWS- at 9:15AM https://t.co/kCMZi0bxEY", "id2": "903634970207539200", "tweet_types": {"deleted_tweet": 0, "retweet": "903634970207539200", "quote_tweet": 0, "reply": 0, "original_tweet": 0}}, {"id": "903635021113765888", "text": "RT @fbcoem: Update from NWS- at 9:15AM https://t.co/kCMZi0bxEY", "created_at": {"$date": "2017-09-01T15:05:52Z"}, "favorites_count": 0, "user": {"screen_name": "E_Sanchize", "name": "MoCityDo\u00f1a", "id": "256234713", "friends": 1125, "followers": 1005, "verified": false, "account_created_at": {"$date": "2011-02-22T23:07:01Z"}, "location": "Mo City, Tx ", "description": "Go Green Remarketing- Best Computers S.A- Best Computers Nicaragua @UHPRES @UHouston @UHCougarFB #HTownTakeover COOG/\u2693\ufe0f Alumni '14"}, "original_text": "Update from NWS- at 9:15AM https://t.co/kCMZi0bxEY", "id2": "903634970207539200", "tweet_types": {"deleted_tweet": 0, "retweet": "903634970207539200", "quote_tweet": 0, "reply": 0, "original_tweet": 0}}, {"id": "903635025295544320", "text": "RT @fbcoem: Update from NWS- at 9:15AM https://t.co/kCMZi0bxEY", "created_at": {"$date": "2017-09-01T15:05:53Z"}, "favorites_count": 0, "user": {"screen_name": "meh95", "name": "Meghan Harris", "id": "32486099", "friends": 2635, "followers": 423, "verified": false, "account_created_at": {"$date": "2009-04-17T17:19:43Z"}, "location": "Texas", "description": "Wife, mother, Aggie Class of 1995!"}, "original_text": "Update from NWS- at 9:15AM https://t.co/kCMZi0bxEY", "id2": "903634970207539200", "tweet_types": {"deleted_tweet": 0, "retweet": "903634970207539200", "quote_tweet": 0, "reply": 0, "original_tweet": 0}}, {"id": "903635077661327360", "text": "RT @fbcoem: Update from NWS- at 9:15AM https://t.co/kCMZi0bxEY", "created_at": {"$date": "2017-09-01T15:06:05Z"}, "favorites_count": 0, "user": {"screen_name": "SherryCISM", "name": "Sherry Cardinal", "id": "768929895351103488", "friends": 26, "followers": 16, "verified": false, "account_created_at": {"$date": "2016-08-25T21:55:47Z"}, "location": "Fort Bend County, Texas", "description": "Sherry's the name, critical incident stress management is my game!"}, "original_text": "Update from NWS- at 9:15AM https://t.co/kCMZi0bxEY", "id2": "903634970207539200", "tweet_types": {"deleted_tweet": 0, "retweet": "903634970207539200", "quote_tweet": 0, "reply": 0, "original_tweet": 0}}, {"id": "903635084527501312", "text": "RT @fbcoem: Update from NWS- at 9:15AM https://t.co/kCMZi0bxEY", "created_at": {"$date": "2017-09-01T15:06:07Z"}, "favorites_count": 0, "user": {"screen_name": "erikmignault", "name": "erikmignault", "id": "15597911", "friends": 348, "followers": 122, "verified": false, "account_created_at": {"$date": "2008-07-25T13:46:58Z"}, "location": "Texas", "description": "Love technology and gadgets - I love to run, and track my runs with multiple apps and wearable tech - Proud Apple Fanboy - HUGE NFL Fan - Father - Husband"}, "original_text": "Update from NWS- at 9:15AM https://t.co/kCMZi0bxEY", "id2": "903634970207539200", "tweet_types": {"deleted_tweet": 0, "retweet": "903634970207539200", "quote_tweet": 0, "reply": 0, "original_tweet": 0}}, {"id": "903635212084629504", "text": "RT @fbcoem: Update from NWS- at 9:15AM https://t.co/kCMZi0bxEY", "created_at": {"$date": "2017-09-01T15:06:37Z"}, "favorites_count": 0, "user": {"screen_name": "TSCRA", "name": "TSCRA", "id": "39814266", "friends": 834, "followers": 2366, "verified": false, "account_created_at": {"$date": "2009-05-13T18:42:40Z"}, "location": "Fort Worth, Texas", "description": "The oldest and largest livestock association in Texas. Protecting the stewards of land and livestock in the Southwest since 1877."}, "original_text": "Update from NWS- at 9:15AM https://t.co/kCMZi0bxEY", "id2": "903634970207539200", "tweet_types": {"deleted_tweet": 0, "retweet": "903634970207539200", "quote_tweet": 0, "reply": 0, "original_tweet": 0}}, {"id": "903635365868789762", "text": "RT @fbcoem: Update from NWS- at 9:15AM https://t.co/kCMZi0bxEY", "created_at": {"$date": "2017-09-01T15:07:14Z"}, "favorites_count": 0, "user": {"screen_name": "troutseth", "name": "Seth Trout", "id": "23882758", "friends": 205, "followers": 253, "verified": false, "account_created_at": {"$date": "2009-03-12T03:04:04Z"}, "location": "Texas", "description": "Husband, father, golfer, homebrewer, technophile (is that a word), productive member of society, concerned American"}, "original_text": "Update from NWS- at 9:15AM https://t.co/kCMZi0bxEY", "id2": "903634970207539200", "tweet_types": {"deleted_tweet": 0, "retweet": "903634970207539200", "quote_tweet": 0, "reply": 0, "original_tweet": 0}}, {"id": "903635507963363334", "text": "RT @fbcoem: Update from NWS- at 9:15AM https://t.co/kCMZi0bxEY", "created_at": {"$date": "2017-09-01T15:07:48Z"}, "favorites_count": 0, "user": {"screen_name": "jeff_horton314", "name": "Jeffrey Horton", "id": "819695511645069316", "friends": 119, "followers": 63, "verified": false, "account_created_at": {"$date": "2017-01-13T00:00:13Z"}, "location": "Texas, USA", "description": null}, "original_text": "Update from NWS- at 9:15AM https://t.co/kCMZi0bxEY", "id2": "903634970207539200", "tweet_types": {"deleted_tweet": 0, "retweet": "903634970207539200", "quote_tweet": 0, "reply": 0, "original_tweet": 0}}, {"id": "903635796263088128", "text": "RT @fbcoem: Update from NWS- at 9:15AM https://t.co/kCMZi0bxEY", "created_at": {"$date": "2017-09-01T15:08:57Z"}, "favorites_count": 0, "user": {"screen_name": "FBCSO", "name": "FBCSO Texas", "id": "71361765", "friends": 178, "followers": 13222, "verified": true, "account_created_at": {"$date": "2009-09-03T21:18:02Z"}, "location": "1410 Williams Way Richmond, TX", "description": "Fort Bend County Sheriff's Office. Sheriff Troy Nehls @SheriffTNehls Facebook: https://t.co/ugn4dn4r2T Subscribe to our YouTube: https://t.co/pEqUP4JgdO"}, "original_text": "Update from NWS- at 9:15AM https://t.co/kCMZi0bxEY", "id2": "903634970207539200", "tweet_types": {"deleted_tweet": 0, "retweet": "903634970207539200", "quote_tweet": 0, "reply": 0, "original_tweet": 0}}, {"id": "903635757709090816", "text": "RT @fbcoem: Update from NWS- at 9:15AM https://t.co/kCMZi0bxEY", "created_at": {"$date": "2017-09-01T15:08:48Z"}, "favorites_count": 0, "user": {"screen_name": "ntheN1CKoftime", "name": "Nick Perez", "id": "16342719", "friends": 273, "followers": 162, "verified": false, "account_created_at": {"$date": "2008-09-18T04:11:35Z"}, "location": "Texas", "description": null}, "original_text": "Update from NWS- at 9:15AM https://t.co/kCMZi0bxEY", "id2": "903634970207539200", "tweet_types": {"deleted_tweet": 0, "retweet": "903634970207539200", "quote_tweet": 0, "reply": 0, "original_tweet": 0}}, {"id": "903636033010589697", "text": "RT @fbcoem: Update from NWS- at 9:15AM https://t.co/kCMZi0bxEY", "created_at": {"$date": "2017-09-01T15:09:53Z"}, "favorites_count": 0, "user": {"screen_name": "Brooksie_253", "name": "Michael Brooks", "id": "364049382", "friends": 539, "followers": 492, "verified": false, "account_created_at": {"$date": "2011-08-29T03:22:47Z"}, "description": "Once in a while you get shown the light, in the strangest of places if you look at it right UH Alum - CMSwag - Go COOGS!"}, "original_text": "Update from NWS- at 9:15AM https://t.co/kCMZi0bxEY", "id2": "903634970207539200", "tweet_types": {"deleted_tweet": 0, "retweet": "903634970207539200", "quote_tweet": 0, "reply": 0, "original_tweet": 0}}, {"id": "903702080308875265", "text": "RT @fbcoem: Update from NWS- at 9:15AM https://t.co/kCMZi0bxEY", "created_at": {"$date": "2017-09-01T19:32:20Z"}, "favorites_count": 0, "user": {"screen_name": "C_Coolidge", "name": "Charlotte L Coolidge", "id": "798890670", "friends": 15752, "followers": 14781, "verified": false, "account_created_at": {"$date": "2012-09-02T19:26:38Z"}, "location": "San Antonio", "description": "Lutheran (Missouri Synod), St. Mary's U BBA '95 (marketing), avid reader, arts & crafts fan, inquisitive, Spurs fan, little drummer girl"}, "original_text": "Update from NWS- at 9:15AM https://t.co/kCMZi0bxEY", "id2": "903634970207539200", "tweet_types": {"deleted_tweet": 0, "retweet": "903634970207539200", "quote_tweet": 0, "reply": 0, "original_tweet": 0}}, {"id": "903752781995102209", "text": "RT @fbcoem: Update from NWS- at 9:15AM https://t.co/kCMZi0bxEY", "created_at": {"$date": "2017-09-01T22:53:48Z"}, "favorites_count": 0, "user": {"screen_name": "adeebrahman73", "name": "Adeeb Rahman", "id": "817787756281790464", "friends": 5000, "followers": 860, "verified": false, "account_created_at": {"$date": "2017-01-07T17:39:29Z"}, "location": "Washington, DC", "description": "Proud father of three. Proud Liberal. Proud lighting designer. Proud Washington Insider. Proud leader of the #TheResistance."}, "original_text": "Update from NWS- at 9:15AM https://t.co/kCMZi0bxEY", "id2": "903634970207539200", "tweet_types": {"deleted_tweet": 0, "retweet": "903634970207539200", "quote_tweet": 0, "reply": 0, "original_tweet": 0}}, {"id": "903677027273777152", "text": "RT @fbcoem: Update from NWS- at 9:15AM https://t.co/kCMZi0bxEY", "created_at": {"$date": "2017-09-01T17:52:47Z"}, "favorites_count": 0, "user": {"screen_name": "TitaniumJanes", "name": "Jane.. Titanium Jane", "id": "2913102942", "friends": 489, "followers": 631, "verified": false, "account_created_at": {"$date": "2014-11-28T23:32:20Z"}, "description": "A woman with a voice. Listen up."}, "original_text": "Update from NWS- at 9:15AM https://t.co/kCMZi0bxEY", "id2": "903634970207539200", "tweet_types": {"deleted_tweet": 0, "retweet": "903634970207539200", "quote_tweet": 0, "reply": 0, "original_tweet": 0}}, {"id": "903638702664163328", "text": "RT @fbcoem: Update from NWS- at 9:15AM https://t.co/kCMZi0bxEY", "created_at": {"$date": "2017-09-01T15:20:30Z"}, "favorites_count": 0, "user": {"screen_name": "strutt1313", "name": "Strutt2abetterme", "id": "929934224", "friends": 1505, "followers": 1645, "verified": false, "account_created_at": {"$date": "2012-11-06T15:16:41Z"}, "location": "Texas, USA", "description": "Run hard, run often,  and have fun running! PRs=1:34:22 half,  3:25 Full."}, "original_text": "Update from NWS- at 9:15AM https://t.co/kCMZi0bxEY", "id2": "903634970207539200", "tweet_types": {"deleted_tweet": 0, "retweet": "903634970207539200", "quote_tweet": 0, "reply": 0, "original_tweet": 0}}, {"id": "903639171071401984", "text": "RT @fbcoem: Update from NWS- at 9:15AM https://t.co/kCMZi0bxEY", "created_at": {"$date": "2017-09-01T15:22:21Z"}, "favorites_count": 0, "user": {"screen_name": "ccmcminn", "name": "Christopher McMinn", "id": "137438586", "friends": 143, "followers": 140, "verified": false, "account_created_at": {"$date": "2010-04-26T19:11:58Z"}, "location": "GOD's Country (Texas)", "description": null}, "original_text": "Update from NWS- at 9:15AM https://t.co/kCMZi0bxEY", "id2": "903634970207539200", "tweet_types": {"deleted_tweet": 0, "retweet": "903634970207539200", "quote_tweet": 0, "reply": 0, "original_tweet": 0}}, {"id": "903639462571212800", "text": "RT @fbcoem: Update from NWS- at 9:15AM https://t.co/kCMZi0bxEY", "created_at": {"$date": "2017-09-01T15:23:31Z"}, "favorites_count": 0, "user": {"screen_name": "SydneyStavinoha", "name": "Sydney Stavinoha", "id": "291512778", "friends": 827, "followers": 576, "verified": false, "account_created_at": {"$date": "2011-05-02T04:14:07Z"}, "location": "Houston | Norman", "description": "Adventurer. Traveler. @UofOklahoma journalism alum. | Skimm'bassador @theskimm"}, "original_text": "Update from NWS- at 9:15AM https://t.co/kCMZi0bxEY", "id2": "903634970207539200", "tweet_types": {"deleted_tweet": 0, "retweet": "903634970207539200", "quote_tweet": 0, "reply": 0, "original_tweet": 0}}, {"id": "903639698962337792", "text": "RT @fbcoem: Update from NWS- at 9:15AM https://t.co/kCMZi0bxEY", "created_at": {"$date": "2017-09-01T15:24:27Z"}, "favorites_count": 0, "user": {"screen_name": "MissouriCityTX", "name": "Missouri City, TX", "id": "58801865", "friends": 192, "followers": 3691, "verified": false, "account_created_at": {"$date": "2009-07-21T14:00:10Z"}, "location": "Missouri City, TX", "description": "Missouri City, Texas -- the Show Me City, is recognized as One of America\u2019s Best Places to Live by CNN/Money magazine and One of America\u2019s Safest Cities."}, "original_text": "Update from NWS- at 9:15AM https://t.co/kCMZi0bxEY", "id2": "903634970207539200", "tweet_types": {"deleted_tweet": 0, "retweet": "903634970207539200", "quote_tweet": 0, "reply": 0, "original_tweet": 0}}, {"id": "903639626073735168", "text": "RT @fbcoem: Update from NWS- at 9:15AM https://t.co/kCMZi0bxEY", "created_at": {"$date": "2017-09-01T15:24:10Z"}, "favorites_count": 0, "user": {"screen_name": "MissouriCityEM", "name": "MissouriCityReady", "id": "444023789", "friends": 88, "followers": 1273, "verified": false, "account_created_at": {"$date": "2011-12-22T20:14:38Z"}, "location": "Missouri City, TX", "description": "Missouri City Emergency Preparedness"}, "original_text": "Update from NWS- at 9:15AM https://t.co/kCMZi0bxEY", "id2": "903634970207539200", "tweet_types": {"deleted_tweet": 0, "retweet": "903634970207539200", "quote_tweet": 0, "reply": 0, "original_tweet": 0}}, {"id": "903641035229863936", "text": "RT @fbcoem: Update from NWS- at 9:15AM https://t.co/kCMZi0bxEY", "created_at": {"$date": "2017-09-01T15:29:46Z"}, "favorites_count": 0, "user": {"screen_name": "mapleda", "name": "deeya maple", "id": "194272989", "friends": 733, "followers": 297, "verified": false, "account_created_at": {"$date": "2010-09-23T20:19:30Z"}, "location": "houston texas", "description": "i'm just me ... one of a kind"}, "original_text": "Update from NWS- at 9:15AM https://t.co/kCMZi0bxEY", "id2": "903634970207539200", "tweet_types": {"deleted_tweet": 0, "retweet": "903634970207539200", "quote_tweet": 0, "reply": 0, "original_tweet": 0}}, {"id": "903636517716983808", "text": "RT @fbcoem: Update from NWS- at 9:15AM https://t.co/kCMZi0bxEY", "created_at": {"$date": "2017-09-01T15:11:49Z"}, "favorites_count": 0, "user": {"screen_name": "ELermaFaltine", "name": "Edith", "id": "113806349", "friends": 222, "followers": 245, "verified": false, "account_created_at": {"$date": "2010-02-13T03:27:10Z"}, "location": "Richmond, TX", "description": "God first! Mom to 4 beautiful boys, wife, sister, daughter, teacher, avid reader, lover of sports. Go #4Faltine, Banditos, UH Cougars, Astros, Texans & Rockets!"}, "original_text": "Update from NWS- at 9:15AM https://t.co/kCMZi0bxEY", "id2": "903634970207539200", "tweet_types": {"deleted_tweet": 0, "retweet": "903634970207539200", "quote_tweet": 0, "reply": 0, "original_tweet": 0}}, {"id": "903636581113880577", "text": "RT @fbcoem: Update from NWS- at 9:15AM https://t.co/kCMZi0bxEY", "created_at": {"$date": "2017-09-01T15:12:04Z"}, "favorites_count": 0, "user": {"screen_name": "b3auty_FulAsh", "name": "Ashlynn", "id": "34649432", "friends": 428, "followers": 156, "verified": false, "account_created_at": {"$date": "2009-04-23T15:59:39Z"}, "description": "Beautiful, Funny, and Down to Earth! #ILoveTheLord"}, "original_text": "Update from NWS- at 9:15AM https://t.co/kCMZi0bxEY", "id2": "903634970207539200", "tweet_types": {"deleted_tweet": 0, "retweet": "903634970207539200", "quote_tweet": 0, "reply": 0, "original_tweet": 0}}, {"id": "903637218018906112", "text": "RT @fbcoem: Update from NWS- at 9:15AM https://t.co/kCMZi0bxEY", "created_at": {"$date": "2017-09-01T15:14:36Z"}, "favorites_count": 0, "user": {"screen_name": "TheChrisMiller5", "name": "Toph", "id": "433089212", "friends": 190, "followers": 323, "verified": false, "account_created_at": {"$date": "2011-12-10T04:01:09Z"}, "location": "Sugar Land / Lubbock", "description": "Texas Tech alumnus. Houston sports enthusiast. Romans 5:8"}, "original_text": "Update from NWS- at 9:15AM https://t.co/kCMZi0bxEY", "id2": "903634970207539200", "tweet_types": {"deleted_tweet": 0, "retweet": "903634970207539200", "quote_tweet": 0, "reply": 0, "original_tweet": 0}}, {"id": "903637152126435328", "text": "RT @fbcoem: Update from NWS- at 9:15AM https://t.co/kCMZi0bxEY", "created_at": {"$date": "2017-09-01T15:14:20Z"}, "favorites_count": 0, "user": {"screen_name": "pjellis0517", "name": "Patricia Ellis", "id": "45055185", "friends": 69, "followers": 21, "verified": false, "account_created_at": {"$date": "2009-06-06T01:47:44Z"}, "location": "Katy, TX", "description": null}, "original_text": "Update from NWS- at 9:15AM https://t.co/kCMZi0bxEY", "id2": "903634970207539200", "tweet_types": {"deleted_tweet": 0, "retweet": "903634970207539200", "quote_tweet": 0, "reply": 0, "original_tweet": 0}}, {"id": "903637465331888129", "text": "RT @fbcoem: Update from NWS- at 9:15AM https://t.co/kCMZi0bxEY", "created_at": {"$date": "2017-09-01T15:15:35Z"}, "favorites_count": 0, "user": {"screen_name": "iniguezmari_", "name": "Mari", "id": "2839573110", "friends": 1490, "followers": 1992, "verified": false, "account_created_at": {"$date": "2014-10-04T04:03:17Z"}, "location": "Houston, TX", "description": "Que tu vida sea bella"}, "original_text": "Update from NWS- at 9:15AM https://t.co/kCMZi0bxEY", "id2": "903634970207539200", "tweet_types": {"deleted_tweet": 0, "retweet": "903634970207539200", "quote_tweet": 0, "reply": 0, "original_tweet": 0}}, {"id": "903637746824224768", "text": "RT @fbcoem: Update from NWS- at 9:15AM https://t.co/kCMZi0bxEY", "created_at": {"$date": "2017-09-01T15:16:42Z"}, "favorites_count": 0, "user": {"screen_name": "marciefinley", "name": "Mrs. Finley", "id": "301204156", "friends": 448, "followers": 290, "verified": false, "account_created_at": {"$date": "2011-05-19T02:12:37Z"}, "description": "Wife to my sweetheart, mommy to the best kiddos ever, math teacher and daughter of the King! \u2022\u2022 beliefs & opinions mine"}, "original_text": "Update from NWS- at 9:15AM https://t.co/kCMZi0bxEY", "id2": "903634970207539200", "tweet_types": {"deleted_tweet": 0, "retweet": "903634970207539200", "quote_tweet": 0, "reply": 0, "original_tweet": 0}}, {"id": "903638315689279488", "text": "RT @fbcoem: Update from NWS- at 9:15AM https://t.co/kCMZi0bxEY", "created_at": {"$date": "2017-09-01T15:18:57Z"}, "favorites_count": 0, "user": {"screen_name": "sarahh_285", "name": "Sarah Hakam\u2122", "id": "2869421919", "friends": 231, "followers": 138, "verified": false, "account_created_at": {"$date": "2014-11-09T19:30:56Z"}, "location": "Starkiller Base", "description": "AHS Troupe 5448 Secretary \ud83c\udfad\n~Why be Normal when you can be Extraordinary~ \u2728\nSnapchat: be_blue822    Lebanon\u2764 \u062d\u0643\u0645 \u0633\u0627\u0631\u0629"}, "original_text": "Update from NWS- at 9:15AM https://t.co/kCMZi0bxEY", "id2": "903634970207539200", "tweet_types": {"deleted_tweet": 0, "retweet": "903634970207539200", "quote_tweet": 0, "reply": 0, "original_tweet": 0}}, {"id": "903638292868059136", "text": "RT @fbcoem: Update from NWS- at 9:15AM https://t.co/kCMZi0bxEY", "created_at": {"$date": "2017-09-01T15:18:52Z"}, "favorites_count": 0, "user": {"screen_name": "SinanAliBana", "name": "Sinan Bana", "id": "752479854", "friends": 114, "followers": 64, "verified": false, "account_created_at": {"$date": "2012-08-12T04:48:16Z"}, "description": "Former Accountant -- Future Physician. Sports and Technology Aficionado. Traveler!"}, "original_text": "Update from NWS- at 9:15AM https://t.co/kCMZi0bxEY", "id2": "903634970207539200", "tweet_types": {"deleted_tweet": 0, "retweet": "903634970207539200", "quote_tweet": 0, "reply": 0, "original_tweet": 0}}]